withoutmem/alu.v
module ALU (
    input [31:0] A,           
    input [31:0] B,           
    input [1:0] ALUOp,        
    input [2:0] funct3,       
    input [4:0] shamt,        
    input [6:0] funct7,      
    output reg [31:0] Result, 
    output Zero,
    output reg Less               
);

    assign Zero = (Result == 32'b0);

    always @(*) begin
        Less = ($signed(A) < $signed(B)) ? 1'b1 : 1'b0;
        
        case (ALUOp)
            2'b00: begin // 算術運算類型
                case (funct3)
                    3'b000: begin // ADD 或 SUB
                        if (funct7 == 7'b0100000)
                            Result = A - B;  // 减法
                        else
                            Result = A + B;  // 加法
                    end
                    3'b100: Result = A ^ B;  // XOR
                    3'b110: Result = A | B;  // OR
                    3'b111: Result = A & B;  // AND
                    default: Result = 32'b0;
                endcase
            end
            2'b01: begin // 移位操作
                case (funct3)
                    3'b001: Result = A << shamt;       // SLL 左移
                    3'b101: begin
                        if (funct7 == 7'b0100000)
                            Result = $signed(A) >>> shamt; // SRA 算術右移
                        else
                            Result = A >> shamt;         // SRL 邏輯右移
                    end
                    default: Result = 32'b0;
                endcase
            end
            2'b10: begin // 比較操作
                case (funct3)
                    3'b010: Result = ($signed(A) < $signed(B)) ? 32'b1 : 32'b0; // SLT 有符號比較
                    3'b011: Result = (A < B) ? 32'b1 : 32'b0;                   // SLTU 無符號比較
                    default: Result = 32'b0;
                endcase
            end
            default: Result = 32'b0;
        endcase
    end

endmodule

regst.v
`timescale 1ns/100ps

module register_file (
    input wire [4:0] Ra,       // rs1
    input wire [4:0] Rb,       // rs2
    input wire [4:0] Rw,       // rd
    input wire [31:0] busW,    // data write
    input wire RegWr,          // enable
    input wire WrClk,          // clk
    output wire [31:0] busA,   // data read 1
    output wire [31:0] busB,   // data read 2
    output wire [31:0] reg1,   // observe register x1
    output wire [31:0] reg2    // observe register x2
);

    // 32條32位元的寄存器
    reg [31:0] registers [31:0];

    // 讀取寄存器 x0~x31
    assign busA = (Ra == 5'b0) ? 32'b0 : registers[Ra];  // x0 永遠為 0
    assign busB = (Rb == 5'b0) ? 32'b0 : registers[Rb];  // x0 永遠為 0

    // x1 和 x2 的額外輸出端口，用於觀察其值
    assign reg1 = registers[1];
    assign reg2 = registers[2];

    // 在時鐘的下降沿進行寫入操作
    always @(negedge WrClk) begin
        if (RegWr && (Rw != 5'b0)) begin  // x0 無法寫入
            registers[Rw] <= busW;
        end
    end

    // 初始化寄存器為 0
    integer i;
    initial begin
        for (i = 0; i < 32; i = i + 1) begin
            registers[i] = 32'b0;
        end
    end
endmodule

withoutmem/decoder.v
module Decoder (
    input [31:0] instr,           
    output reg [4:0] rs1,         
    output reg [4:0] rs2,         
    output reg [4:0] rd,          
    output reg [2:0] funct3,      
    output reg [6:0] funct7,      
    output reg [6:0] opcode,      
    output reg [31:0] imm,        
    output reg [4:0] shamt,       
    output reg RegWrite,          
    output reg MemRead,           
    output reg MemWrite,          
    output reg MemToReg,          
    output reg ALUSrc,            
    output reg Branch,            
    output reg Jump,              
    output reg [1:0] ALUOp        
);

    always @(*) begin
        // Extract fields from the instruction
        opcode = instr[6:0];
        rd = instr[11:7];
        funct3 = instr[14:12];
        rs1 = instr[19:15];
        rs2 = instr[24:20];
        funct7 = instr[31:25];

        // Default values
        shamt = instr[24:20];  
        imm = 32'b0;
        RegWrite = 0;
        MemRead = 0;
        MemWrite = 0;
        MemToReg = 0;
        ALUSrc = 0;
        Branch = 0;
        Jump = 0;
        ALUOp = 2'b00;

        case (opcode)
            7'b0110011: begin // R-Type (e.g., add, sub, and, or)
                RegWrite = 1;
                ALUSrc = 0;
                MemToReg = 0;
                MemRead = 0;
                MemWrite = 0;
                Branch = 0;
                ALUOp = 2'b00; // 算術類
            end
            7'b0010011: begin // I-Type for ALU immediate (e.g., addi, slli)
                RegWrite = 1;
                ALUSrc = 1;
                MemToReg = 0;
                MemRead = 0;
                MemWrite = 0;
                Branch = 0;
                ALUOp = (funct3 == 3'b001 || funct3 == 3'b101) ? 2'b01 : 2'b00; // 移位操作 or 算術操作
                imm = {{20{instr[31]}}, instr[31:20]};
                if (funct3 == 3'b001 || funct3 == 3'b101) begin // Shift instructions with immediate
                    shamt = instr[24:20];
                end
            end
            7'b0000011: begin // I-Type Load (e.g., lw, lb)
                RegWrite = 1;
                ALUSrc = 1;
                MemToReg = 1;
                MemRead = 1;
                MemWrite = 0;
                Branch = 0;
                ALUOp = 2'b00; // 加法操作
                imm = {{20{instr[31]}}, instr[31:20]};
            end
            7'b0100011: begin // S-Type Store (e.g., sw, sb)
                RegWrite = 0;
                ALUSrc = 1;
                MemToReg = 0;
                MemRead = 0;
                MemWrite = 1;
                Branch = 0;
                ALUOp = 2'b00; // 加法操作
                imm = {{20{instr[31]}}, instr[31:25], instr[11:7]};
            end
            7'b1100011: begin // B-Type Branch (e.g., beq, bne)
                RegWrite = 0;
                ALUSrc = 0;
                MemToReg = 0;
                MemRead = 0;
                MemWrite = 0;
                Branch = 1;
                ALUOp = 2'b10; // 比較操作
                imm = {{20{instr[31]}}, instr[7], instr[30:25], instr[11:8], 1'b0};
            end
            7'b1101111: begin // J-Type Jump (e.g., jal)
                RegWrite = 1;
                ALUSrc = 1;
                MemToReg = 0;
                MemRead = 0;
                MemWrite = 0;
                Branch = 0;
                Jump = 1;
                ALUOp = 2'b00; // 加法操作
                imm = {{12{instr[31]}}, instr[19:12], instr[20], instr[30:21], 1'b0};
            end
            7'b1100111: begin // I-Type Jump Register (e.g., jalr)
                RegWrite = 1;
                ALUSrc = 1;
                MemToReg = 0;
                MemRead = 0;
                MemWrite = 0;
                Branch = 0;
                Jump = 1;
                ALUOp = 2'b00; // 加法操作
                imm = {{20{instr[31]}}, instr[31:20]};
            end
            default: begin
                RegWrite = 0;
                MemRead = 0;
                MemWrite = 0;
                MemToReg = 0;
                ALUSrc = 0;
                Branch = 0;
                Jump = 0;
                ALUOp = 2'b00;
                imm = 32'b0;
                shamt = 5'b0;
            end
        endcase
    end

endmodule

instmem.v
`timescale 1ns/100ps

module Instr_Mem (
    input wire [31:0] addr,  // programming counter addr (motion that should do)
    output reg [31:0] instr  // instr output
);

    reg [31:0] memory [0:65535]; //64k instr = 128kbyte
    // initial (wouldn't change if u don't want to do more)
    initial begin
// ********************整數運算*********************
// opcode rs rs2 rd imm	
//(R-type)
        memory[0]  = 32'b0000000_00011_00010_000_00001_0110011; // add x1, x2, x3
        memory[1]  = 32'b0100000_00011_00010_000_00001_0110011; // sub x1, x2, x3
        memory[2]  = 32'b0000000_00011_00010_100_00001_0110011; // xor x1, x2, x3
        memory[3]  = 32'b0000000_00011_00010_110_00001_0110011; // or x1, x2, x3
        memory[4]  = 32'b0000000_00011_00010_111_00001_0110011; // and x1, x2, x3
        memory[5]  = 32'b0000000_00011_00010_001_00001_0110011; // sll x1, x2, x3
        memory[6]  = 32'b0000000_00011_00010_101_00001_0110011; // srl x1, x2, x3
        memory[7]  = 32'b0100000_00011_00010_101_00001_0110011; // sra x1, x2, x3
        memory[8]  = 32'b0000000_00011_00010_010_00001_0110011; // slt x1, x2, x3
        memory[9]  = 32'b0000000_00011_00010_011_00001_0110011; // sltu x1, x2, x3
        
//(I-type)						       								
        memory[10] = 32'b000000000001_00010_000_00001_0010011; // addi x1, x2, 1
        memory[11] = 32'b000000000001_00010_100_00001_0010011; // xori x1, x2, 1
        memory[12] = 32'b000000000001_00010_110_00001_0010011; // ori x1, x2, 1
        memory[13] = 32'b000000000001_00010_111_00001_0010011; // andi x1, x2, 1
        memory[14] = 32'b000000000001_00010_001_00001_0010011; // slli x1, x2, 1 (shamt) 
        memory[15] = 32'b000000000001_00010_101_00001_0010011; // srli x1, x2, 1 (shamt)
        memory[16] = 32'b010000000001_00010_101_00001_0010011; // srai x1, x2, 1 (shamt)
        memory[17] = 32'b000000000001_00010_010_00001_0010011; // slti x1, x2, 1
        memory[18] = 32'b000000000001_00010_011_00001_0010011; // sltiu x1, x2, 1
//(U-type)
	memory[19] = 32'b000000000001_00010_000_00001_0110111; // lui imm rd 1
        memory[20] = 32'b000000000001_00010_100_00001_0010111; // auipe 
// ********************條件跳轉*********************
// (B-type)
        memory[21] = 32'b0000000_00010_00001_000_00010_1100011; // beq x1, x2, offset
        memory[22] = 32'b0000000_00010_00001_001_00010_1100011; // bne x1, x2, offset
        memory[23] = 32'b0000000_00010_00001_100_00010_1100011; // blt x1, x2, offset
        memory[24] = 32'b0000000_00010_00001_101_00010_1100011; // bge x1, x2, offset
        memory[25] = 32'b0000000_00010_00001_110_00010_1100011; // bltu x1, x2, offset
        memory[26] = 32'b0000000_00010_00001_111_00010_1100011; // bgeu x1, x2, offset
// (J-type)
        memory[27] = 32'b000000000100_00000_110_00001_1101111; // jal x1, offset
        memory[28] = 32'b000000000100_00001_000_00010_1100111; // jalr x2, x1, offset

// ********************reading instru*********************
        memory[29] = 32'b000000000000_00101_010_00100_0000011;  // lw x4, 0(x5)
        memory[30] = 32'b000000000000_00101_000_00100_0000011;  // lb x4, 0(x5)
        memory[31] = 32'b000000000000_00101_001_00100_0000011;  // lh x4, 0(x5)
        memory[32] = 32'b000000000000_00101_100_00100_0000011;  // lbu x4, 0(x5)
        memory[33] = 32'b000000000000_00101_101_00100_0000011;  // lhu x4, 0(x5)
        memory[34] = 32'b0000000_00001_00010_010_00000_0100011; // sw x1, 0(x2)
        memory[35] = 32'b0000000_00001_00010_000_00000_0100011; // sb x1, 0(x2)
        memory[36] = 32'b0000000_00001_00010_001_00000_0100011; // sh x1, 0(x2)

//********************pesudo instr*********************
        memory[37] = 32'b000000000000_00000_000_00000_0010011; // nop (addi x0, x0, 0)
        memory[38] = 32'b000000000000_00001_000_00010_0110011; // mv x2, x1 (add x2, x1, x0)
        memory[39] = 32'b000000000000_00000_000_00001_0010011; // li x1, 0 (addi x1, x0, 0)
        memory[40] = 32'b000000000100_00000_110_00001_1101111; // call (jal x1, offset)
        memory[41] = 32'b000000000000_00001_000_00010_1100111; // ret (jalr x0, x1, 0)


    end
// 共41條指令
    // IF
    always @(*) begin
        instr = memory[addr[17:2]]; // addr[17:2]
	// 2^16 = 65535 
	// 每條指令間隔4bytes +4 > 省略01 ＝ 1 / 00 ＝ 0 / 11 ＝ 3 / 10 ＝ 2 的可能
    end
endmodule

withoutmem/pc.v
`timescale 1ns/100ps

module PC (
    input wire clk,             
    input wire reset,           
    input wire [31:0] next_pc,  
    output reg [31:0] pc         
);

  
    initial begin
        pc = 32'b0;
    end


    always @(posedge clk or posedge reset) begin
        if (reset) begin
            pc <= 32'b0;          
        end else begin
            pc <= next_pc;        
        end
    end

endmodule

withoutmem/cpupart.v
`timescale 1ns/100ps

module CPU (
    input wire clk,
    input wire reset
);

    wire [31:0] pc, next_pc, instr, busA, busB, imm, alu_result;
    wire [4:0] rs1, rs2, rd, shamt;
    wire [2:0] funct3;
    wire [6:0] funct7, opcode;
    wire RegWrite, MemRead, MemWrite, MemToReg, ALUSrc, Branch, Jump;
    wire [1:0] ALUOp;
    wire Zero, Less;

    // Program Counter (PC)
    PC pc_reg (
        .clk(clk),
        .reset(reset),
        .next_pc(next_pc),
        .pc(pc)
    );

    // Instruction Memory
    Instr_Mem instr_mem (
        .addr(pc),
        .instr(instr)
    );

    // Decoder
    Decoder decoder (
        .instr(instr),
        .rs1(rs1),
        .rs2(rs2),
        .rd(rd),
        .funct3(funct3),
        .funct7(funct7),
        .opcode(opcode),
        .imm(imm),
        .shamt(shamt),
        .RegWrite(RegWrite),
        .MemRead(MemRead),
        .MemWrite(MemWrite),
        .MemToReg(MemToReg),
        .ALUSrc(ALUSrc),
        .Branch(Branch),
        .Jump(Jump),
        .ALUOp(ALUOp)
    );

    // Register File
    register_file reg_file (
        .Ra(rs1),
        .Rb(rs2),
        .Rw(rd),
        .busW(alu_result),     
        .RegWr(RegWrite),      
        .WrClk(clk),
        .busA(busA),
        .busB(busB)
    );

    // ALU
    ALU alu (
        .A(busA),
        .B(ALUSrc ? imm : busB),
        .ALUOp(ALUOp),
        .funct3(funct3),
        .shamt(shamt),
        .funct7(funct7),
        .Result(alu_result),
        .Zero(Zero),
        .Less(Less)
    );

    // PC Update Logic
    assign next_pc = pc + 4; // 每次 PC 增加 4

endmodule

withoutmem/tb.v
`timescale 1ns/100ps

module CPU_tb;
    reg clk;
    reg reset;
    wire [31:0] pc, instr, busA, busB, imm, alu_result;
    wire [4:0] rs1, rs2, rd, shamt;
    wire [2:0] funct3;
    wire [6:0] funct7, opcode;
    wire RegWrite, MemRead, MemWrite, MemToReg, ALUSrc, Branch, Jump;
    wire [1:0] ALUOp;
    wire Zero, Less;

    // Instantiate CPU
    CPU cpu (
        .clk(clk),
        .reset(reset)
    );

    // Assign signals for monitoring
    assign pc = cpu.pc_reg.pc;
    assign instr = cpu.instr_mem.instr;
    assign rs1 = cpu.decoder.rs1;
    assign rs2 = cpu.decoder.rs2;
    assign rd = cpu.decoder.rd;
    assign funct3 = cpu.decoder.funct3;
    assign funct7 = cpu.decoder.funct7;
    assign opcode = cpu.decoder.opcode;
    assign imm = cpu.decoder.imm;
    assign shamt = cpu.decoder.shamt;
    assign RegWrite = cpu.decoder.RegWrite;
    assign MemRead = cpu.decoder.MemRead;
    assign MemWrite = cpu.decoder.MemWrite;
    assign MemToReg = cpu.decoder.MemToReg;
    assign ALUSrc = cpu.decoder.ALUSrc;
    assign Branch = cpu.decoder.Branch;
    assign Jump = cpu.decoder.Jump;
    assign ALUOp = cpu.decoder.ALUOp;
    assign busA = cpu.reg_file.busA;
    assign busB = cpu.reg_file.busB;
    assign alu_result = cpu.alu.Result;

    // Initialize register values for testing
    initial begin
        clk = 1;
        reset = 1;
        #1
        reset = 0;
        
        // Set initial register values for testing
        cpu.reg_file.registers[2] = 10; // x2 = 10
        cpu.reg_file.registers[3] = 20; // x3 = 20

        #200;
        $finish;
    end

    // Clock Generation
    always #5 clk = ~clk;

    // Monitor output at each clock cycle
    initial begin
        $monitor("Time: %0t | PC: %h | Instr: %h | rs1: %h | rs2: %h | rd: %h | funct3: %h | funct7: %h | opcode: %h | imm: %h | shamt: %h | RegWrite: %b | MemRead: %b | MemWrite: %b | ALUSrc: %b | Branch: %b | Jump: %b | ALUOp: %b | busA: %h | busB: %h | ALU Result: %h", 
                 $time, pc, instr, rs1, rs2, rd, funct3, funct7, opcode, imm, shamt, RegWrite, MemRead, MemWrite, ALUSrc, Branch, Jump, ALUOp, busA, busB, alu_result);
    end

    initial begin
        $dumpfile("cpu_tb.vcd");
        $dumpvars;
    end
endmodule

withoutmem/cpu_tb.vcd
$date
	Sat Oct  5 21:21:35 2024
$end
$version
	Icarus Verilog
$end
$timescale
	100ps
$end
$scope module CPU_tb $end
$var wire 2 ! ALUOp [1:0] $end
$var wire 1 " ALUSrc $end
$var wire 1 # Branch $end
$var wire 1 $ Jump $end
$var wire 1 % MemRead $end
$var wire 1 & MemToReg $end
$var wire 1 ' MemWrite $end
$var wire 1 ( RegWrite $end
$var wire 32 ) alu_result [31:0] $end
$var wire 32 * busA [31:0] $end
$var wire 32 + busB [31:0] $end
$var wire 3 , funct3 [2:0] $end
$var wire 7 - funct7 [6:0] $end
$var wire 32 . imm [31:0] $end
$var wire 32 / instr [31:0] $end
$var wire 7 0 opcode [6:0] $end
$var wire 32 1 pc [31:0] $end
$var wire 5 2 rd [4:0] $end
$var wire 5 3 rs1 [4:0] $end
$var wire 5 4 rs2 [4:0] $end
$var wire 5 5 shamt [4:0] $end
$var reg 1 6 clk $end
$var reg 1 7 reset $end
$scope module cpu $end
$var wire 1 6 clk $end
$var wire 1 7 reset $end
$var wire 5 8 shamt [4:0] $end
$var wire 5 9 rs2 [4:0] $end
$var wire 5 : rs1 [4:0] $end
$var wire 5 ; rd [4:0] $end
$var wire 32 < pc [31:0] $end
$var wire 7 = opcode [6:0] $end
$var wire 32 > next_pc [31:0] $end
$var wire 32 ? instr [31:0] $end
$var wire 32 @ imm [31:0] $end
$var wire 7 A funct7 [6:0] $end
$var wire 3 B funct3 [2:0] $end
$var wire 32 C busB [31:0] $end
$var wire 32 D busA [31:0] $end
$var wire 32 E alu_result [31:0] $end
$var wire 1 F Zero $end
$var wire 1 G RegWrite $end
$var wire 1 H MemWrite $end
$var wire 1 I MemToReg $end
$var wire 1 J MemRead $end
$var wire 1 K Less $end
$var wire 1 L Jump $end
$var wire 1 M Branch $end
$var wire 1 N ALUSrc $end
$var wire 2 O ALUOp [1:0] $end
$scope module alu $end
$var wire 32 P B [31:0] $end
$var wire 5 Q shamt [4:0] $end
$var wire 7 R funct7 [6:0] $end
$var wire 3 S funct3 [2:0] $end
$var wire 1 F Zero $end
$var wire 2 T ALUOp [1:0] $end
$var wire 32 U A [31:0] $end
$var reg 1 K Less $end
$var reg 32 V Result [31:0] $end
$upscope $end
$scope module decoder $end
$var wire 32 W instr [31:0] $end
$var reg 2 X ALUOp [1:0] $end
$var reg 1 N ALUSrc $end
$var reg 1 M Branch $end
$var reg 1 L Jump $end
$var reg 1 J MemRead $end
$var reg 1 I MemToReg $end
$var reg 1 H MemWrite $end
$var reg 1 G RegWrite $end
$var reg 3 Y funct3 [2:0] $end
$var reg 7 Z funct7 [6:0] $end
$var reg 32 [ imm [31:0] $end
$var reg 7 \ opcode [6:0] $end
$var reg 5 ] rd [4:0] $end
$var reg 5 ^ rs1 [4:0] $end
$var reg 5 _ rs2 [4:0] $end
$var reg 5 ` shamt [4:0] $end
$upscope $end
$scope module instr_mem $end
$var wire 32 a addr [31:0] $end
$var reg 32 b instr [31:0] $end
$upscope $end
$scope module pc_reg $end
$var wire 1 6 clk $end
$var wire 32 c next_pc [31:0] $end
$var wire 1 7 reset $end
$var reg 32 d pc [31:0] $end
$upscope $end
$scope module reg_file $end
$var wire 5 e Ra [4:0] $end
$var wire 5 f Rb [4:0] $end
$var wire 1 G RegWr $end
$var wire 5 g Rw [4:0] $end
$var wire 1 6 WrClk $end
$var wire 32 h busW [31:0] $end
$var wire 32 i reg1 [31:0] $end
$var wire 32 j reg2 [31:0] $end
$var wire 32 k busB [31:0] $end
$var wire 32 l busA [31:0] $end
$var integer 32 m i [31:0] $end
$upscope $end
$upscope $end
$upscope $end
$enddefinitions $end
#0
$dumpvars
b100000 m
b0 l
b0 k
b0 j
b0 i
b0 h
b1 g
b11 f
b10 e
b0 d
b100 c
b1100010000000010110011 b
b0 a
b11 `
b11 _
b10 ^
b1 ]
b110011 \
b0 [
b0 Z
b0 Y
b0 X
b1100010000000010110011 W
b0 V
b0 U
b0 T
b0 S
b0 R
b11 Q
b0 P
b0 O
0N
0M
0L
0K
0J
0I
0H
1G
1F
b0 E
b0 D
b0 C
b0 B
b0 A
b0 @
b1100010000000010110011 ?
b100 >
b110011 =
b0 <
b1 ;
b10 :
b11 9
b11 8
17
16
b11 5
b11 4
b10 3
b1 2
b0 1
b110011 0
b1100010000000010110011 /
b0 .
b0 -
b0 ,
b0 +
b0 *
b0 )
1(
0'
0&
0%
0$
0#
0"
b0 !
$end
#10
1K
b10100 P
0F
b11110 )
b11110 E
b11110 V
b11110 h
b10100 +
b10100 C
b10100 k
b1010 *
b1010 D
b1010 U
b1010 l
b1010 j
07
#50
b11110 i
06
#100
b11111111111111111111111111110110 )
b11111111111111111111111111110110 E
b11111111111111111111111111110110 V
b11111111111111111111111111110110 h
1(
1G
b100000 -
b100000 A
b100000 R
b100000 Z
b1000000001100010000000010110011 /
b1000000001100010000000010110011 ?
b1000000001100010000000010110011 W
b1000000001100010000000010110011 b
b1000 >
b1000 c
b100 1
b100 <
b100 a
b100 d
16
#150
b11111111111111111111111111110110 i
06
#200
b11110 )
b11110 E
b11110 V
b11110 h
1(
1G
b0 -
b0 A
b0 R
b0 Z
b100 ,
b100 B
b100 S
b100 Y
b1100010100000010110011 /
b1100010100000010110011 ?
b1100010100000010110011 W
b1100010100000010110011 b
b1100 >
b1100 c
b1000 1
b1000 <
b1000 a
b1000 d
16
#250
b11110 i
06
#300
1(
1G
b110 ,
b110 B
b110 S
b110 Y
b1100010110000010110011 /
b1100010110000010110011 ?
b1100010110000010110011 W
b1100010110000010110011 b
b10000 >
b10000 c
b1100 1
b1100 <
b1100 a
b1100 d
16
#350
06
#400
1F
b0 )
b0 E
b0 V
b0 h
1(
1G
b111 ,
b111 B
b111 S
b111 Y
b1100010111000010110011 /
b1100010111000010110011 ?
b1100010111000010110011 W
b1100010111000010110011 b
b10100 >
b10100 c
b10000 1
b10000 <
b10000 a
b10000 d
16
#450
b0 i
06
#500
1(
1G
b1 ,
b1 B
b1 S
b1 Y
b1100010001000010110011 /
b1100010001000010110011 ?
b1100010001000010110011 W
b1100010001000010110011 b
b11000 >
b11000 c
b10100 1
b10100 <
b10100 a
b10100 d
16
#550
06
#600
1(
1G
b101 ,
b101 B
b101 S
b101 Y
b1100010101000010110011 /
b1100010101000010110011 ?
b1100010101000010110011 W
b1100010101000010110011 b
b11100 >
b11100 c
b11000 1
b11000 <
b11000 a
b11000 d
16
#650
06
#700
1(
1G
b100000 -
b100000 A
b100000 R
b100000 Z
b1000000001100010101000010110011 /
b1000000001100010101000010110011 ?
b1000000001100010101000010110011 W
b1000000001100010101000010110011 b
b100000 >
b100000 c
b11100 1
b11100 <
b11100 a
b11100 d
16
#750
06
#800
1(
1G
b0 -
b0 A
b0 R
b0 Z
b10 ,
b10 B
b10 S
b10 Y
b1100010010000010110011 /
b1100010010000010110011 ?
b1100010010000010110011 W
b1100010010000010110011 b
b100100 >
b100100 c
b100000 1
b100000 <
b100000 a
b100000 d
16
#850
06
#900
1(
1G
b11 ,
b11 B
b11 S
b11 Y
b1100010011000010110011 /
b1100010011000010110011 ?
b1100010011000010110011 W
b1100010011000010110011 b
b101000 >
b101000 c
b100100 1
b100100 <
b100100 a
b100100 d
16
#950
06
#1000
0K
b1 P
b0 +
b0 C
b0 k
0F
b1011 )
b1011 E
b1011 V
b1011 h
b1 .
b1 @
b1 [
1"
1N
1(
1G
b1 5
b1 8
b1 Q
b1 `
b1 4
b1 9
b1 _
b1 f
b0 ,
b0 B
b0 S
b0 Y
b10011 0
b10011 =
b10011 \
b100010000000010010011 /
b100010000000010010011 ?
b100010000000010010011 W
b100010000000010010011 b
b101100 >
b101100 c
b101000 1
b101000 <
b101000 a
b101000 d
16
#1050
b1011 +
b1011 C
b1011 k
b1011 i
06
#1100
1"
1N
1(
1G
b1 .
b1 @
b1 [
b100 ,
b100 B
b100 S
b100 Y
b100010100000010010011 /
b100010100000010010011 ?
b100010100000010010011 W
b100010100000010010011 b
b110000 >
b110000 c
b101100 1
b101100 <
b101100 a
b101100 d
16
#1150
06
#1200
1"
1N
1(
1G
b1 .
b1 @
b1 [
b110 ,
b110 B
b110 S
b110 Y
b100010110000010010011 /
b100010110000010010011 ?
b100010110000010010011 W
b100010110000010010011 b
b110100 >
b110100 c
b110000 1
b110000 <
b110000 a
b110000 d
16
#1250
06
#1300
1F
b0 )
b0 E
b0 V
b0 h
1"
1N
1(
1G
b1 .
b1 @
b1 [
b111 ,
b111 B
b111 S
b111 Y
b100010111000010010011 /
b100010111000010010011 ?
b100010111000010010011 W
b100010111000010010011 b
b111000 >
b111000 c
b110100 1
b110100 <
b110100 a
b110100 d
16
#1350
b0 +
b0 C
b0 k
b0 i
06
#1400
0F
b10100 )
b10100 E
b10100 V
b10100 h
b1 !
b1 O
b1 T
b1 X
1"
1N
1(
1G
b1 .
b1 @
b1 [
b1 ,
b1 B
b1 S
b1 Y
b100010001000010010011 /
b100010001000010010011 ?
b100010001000010010011 W
b100010001000010010011 b
b111100 >
b111100 c
b111000 1
b111000 <
b111000 a
b111000 d
16
#1450
b10100 +
b10100 C
b10100 k
b10100 i
06
#1500
b101 )
b101 E
b101 V
b101 h
b1 !
b1 O
b1 T
b1 X
1"
1N
1(
1G
b1 .
b1 @
b1 [
b101 ,
b101 B
b101 S
b101 Y
b100010101000010010011 /
b100010101000010010011 ?
b100010101000010010011 W
b100010101000010010011 b
b1000000 >
b1000000 c
b111100 1
b111100 <
b111100 a
b111100 d
16
#1550
b101 +
b101 C
b101 k
b101 i
06
#1600
1K
b10000000001 P
b1 !
b1 O
b1 T
b1 X
1"
1N
1(
1G
b10000000001 .
b10000000001 @
b10000000001 [
b100000 -
b100000 A
b100000 R
b100000 Z
b1000000000100010101000010010011 /
b1000000000100010101000010010011 ?
b1000000000100010101000010010011 W
b1000000000100010101000010010011 b
b1000100 >
b1000100 c
b1000000 1
b1000000 <
b1000000 a
b1000000 d
16
#1650
06
#1700
0K
b1 P
1F
b0 )
b0 E
b0 V
b0 h
b0 !
b0 O
b0 T
b0 X
1"
1N
1(
1G
b1 .
b1 @
b1 [
b0 -
b0 A
b0 R
b0 Z
b10 ,
b10 B
b10 S
b10 Y
b100010010000010010011 /
b100010010000010010011 ?
b100010010000010010011 W
b100010010000010010011 b
b1001000 >
b1001000 c
b1000100 1
b1000100 <
b1000100 a
b1000100 d
16
#1750
b0 +
b0 C
b0 k
b0 i
06
#1800
1"
1N
1(
1G
b1 .
b1 @
b1 [
b11 ,
b11 B
b11 S
b11 Y
b100010011000010010011 /
b100010011000010010011 ?
b100010011000010010011 W
b100010011000010010011 b
b1001100 >
b1001100 c
b1001000 1
b1001000 <
b1001000 a
b1001000 d
16
#1850
06
#1900
b0 P
0F
b1010 )
b1010 E
b1010 V
b1010 h
b0 5
b0 8
b0 Q
b0 `
0"
0N
0(
0G
b0 .
b0 @
b0 [
b0 ,
b0 B
b0 S
b0 Y
b110111 0
b110111 =
b110111 \
b100010000000010110111 /
b100010000000010110111 ?
b100010000000010110111 W
b100010000000010110111 b
b1010000 >
b1010000 c
b1001100 1
b1001100 <
b1001100 a
b1001100 d
16
#1950
06
#2000
b0 5
b0 8
b0 Q
b0 `
b100 ,
b100 B
b100 S
b100 Y
b10111 0
b10111 =
b10111 \
b100010100000010010111 /
b100010100000010010111 ?
b100010100000010010111 W
b100010100000010010111 b
b1010100 >
b1010100 c
b1010000 1
b1010000 <
b1010000 a
b1010000 d
16
