mem.v
`timescale 1ns/100ps

module DataMemory (
    input wire clk,                
    input wire MemRead,            
    input wire MemWrite,           
    input wire [31:0] addr,        
    input wire [31:0] write_data,  
    output reg [31:0] read_data    
);

    reg [31:0] memory [0:65535];  
    integer i;
    initial begin
        for (i = 0; i < 65536; i = i + 1) begin
            memory[i] = 32'b0;
        end
    end
    always @(negedge clk) begin
        if (MemWrite) begin
            memory[addr[15:0] >> 2] <= write_data;  
        end
    end
    always @(posedge clk) begin
        if (MemRead) begin
            read_data <= memory[addr[15:0] >> 2];   
        end
    end
endmodule

alu.v
module ALU (
    input [31:0] A,           
    input [31:0] B,           
    input [1:0] ALUOp,        
    input [2:0] funct3,       
    input [4:0] shamt,        
    input [6:0] funct7,      
    output reg [31:0] Result, 
    output Zero,
    output reg Less               
);

    assign Zero = (Result == 32'b0);

    always @(*) begin
        Less = ($signed(A) < $signed(B)) ? 1'b1 : 1'b0;
        
        case (ALUOp)
            2'b00: begin // 算術運算類型
                case (funct3)
                    3'b000: begin // ADD 或 SUB
                        if (funct7 == 7'b0100000)
                            Result = A - B;  // 减法
                        else
                            Result = A + B;  // 加法
                    end
                    3'b100: Result = A ^ B;  // XOR
                    3'b110: Result = A | B;  // OR
                    3'b111: Result = A & B;  // AND
                    default: Result = 32'b0;
                endcase
            end
            2'b01: begin // 移位操作
                case (funct3)
                    3'b001: Result = A << shamt;       // SLL 左移
                    3'b101: begin
                        if (funct7 == 7'b0100000)
                            Result = $signed(A) >>> shamt; // SRA 算術右移
                        else
                            Result = A >> shamt;         // SRL 邏輯右移
                    end
                    default: Result = 32'b0;
                endcase
            end
            2'b10: begin // 比較操作
                case (funct3)
                    3'b010: Result = ($signed(A) < $signed(B)) ? 32'b1 : 32'b0; // SLT 有符號比較
                    3'b011: Result = (A < B) ? 32'b1 : 32'b0;                   // SLTU 無符號比較
                    default: Result = 32'b0;
                endcase
            end
            default: Result = 32'b0;
        endcase
    end

endmodule

regst.v
`timescale 1ns/100ps


module register_file (
    input wire [4:0] Ra,       //r1
    input wire [4:0] Rb,       //r2
    input wire [4:0] Rw,       // rd
    input wire [31:0] busW,    // data write 1
    input wire RegWr,          // enable
    input wire WrClk,          // clk
    output wire [31:0] busA,   // data read 1
    output wire [31:0] busB    // data read 2
);

    // 32條32位元的reg
    reg [31:0] registers [31:0];

    // 讀取reg x0~x31? (使用條件運算子 a = (b)?c:d >> if b = 1 a = c / b = 0 a = d)
    assign busA = (Ra == 5'b0) ? 32'b0 : registers[Ra];  // x0常數限制
    assign busB = (Rb == 5'b0) ? 32'b0 : registers[Rb];  // x0常數限制

    // 寫入於下降寫入
    always @(negedge WrClk) begin
        if (RegWr && Rw ) begin  
            registers[Rw] <= busW;
        end
    end


   
    integer i;
    initial begin
        for (i = 0; i < 32; i = i + 1) begin
            registers[i] = 32'b0;
        end
    end
endmodule

control.v
module ControlUnit (
    input wire [6:0] opcode,       
    input wire [2:0] funct3,      
    input wire [6:0] funct7,       
    output reg RegWrite,           
    output reg MemWrite,        
    output reg MemRead,          
    output reg MemToReg,        
    output reg ALUSrc,            
    output reg Branch,            
    output reg Jump,               
    output reg [1:0] ALUOp       
);

    always @(*) begin
        RegWrite = 0;
        MemWrite = 0;
        MemRead = 0;
        MemToReg = 0;
        ALUSrc = 0;
        Branch = 0;
        Jump = 0;
        ALUOp = 2'b00;

        case (opcode)
            7'b0110011: begin  // R-Type (add, sub, etc.)
                RegWrite = 1;
                MemWrite = 0;
                MemRead = 0;
                MemToReg = 0;
                ALUSrc = 0;
                Branch = 0;
                ALUOp = 2'b10;  // ALU operation (determined by funct3 and funct7)
            end
            7'b0000011: begin  // I-Type (load)
                RegWrite = 1;
                MemWrite = 0;
                MemRead = 1;
                MemToReg = 1;
                ALUSrc = 1;
                Branch = 0;
                ALUOp = 2'b00;  // ALU operation (add for address calculation)
            end
            7'b0100011: begin  // S-Type (store)
                RegWrite = 0;
                MemWrite = 1;
                MemRead = 0;
                MemToReg = 0;
                ALUSrc = 1;
                Branch = 0;
                ALUOp = 2'b00;  // ALU operation (add for address calculation)
            end
            7'b1100011: begin  // B-Type (branch)
                RegWrite = 0;
                MemWrite = 0;
                MemRead = 0;
                MemToReg = 0;
                ALUSrc = 0;
                Branch = 1;
                ALUOp = 2'b01;  // ALU operation (sub for comparison)
            end
            7'b1101111: begin  // J-Type (jal)
                RegWrite = 1;
                MemWrite = 0;
                MemRead = 0;
                MemToReg = 0;
                ALUSrc = 0;
                Branch = 0;
                Jump = 1;     
                ALUOp = 2'b00; 
            end
            7'b1100111: begin  // J-Type (jalr)
                RegWrite = 1;
                MemWrite = 0;
                MemRead = 0;
                MemToReg = 0;
                ALUSrc = 1;
                Branch = 0;
                Jump = 1;    
                ALUOp = 2'b00;  
            end
            default: begin

            end
        endcase
    end
endmodule

instmem.v
`timescale 1ns/100ps

module Instr_Mem (
    input wire [31:0] addr,  // programming counter addr (motion that should do)
    output reg [31:0] instr  // instr output
);

    reg [31:0] memory [0:65535]; //64k instr = 128kbyte
    // initial (wouldn't change if u don't want to do more)
    initial begin
// ********************整數運算*********************
// opcode rs rs2 rd imm	
//(R-type)
        memory[0]  = 32'b0000000_00011_00010_000_00001_0110011; // add x1, x2, x3
        memory[1]  = 32'b0100000_00011_00010_000_00001_0110011; // sub x1, x2, x3
        memory[2]  = 32'b0000000_00011_00010_100_00001_0110011; // xor x1, x2, x3
        memory[3]  = 32'b0000000_00011_00010_110_00001_0110011; // or x1, x2, x3
        memory[4]  = 32'b0000000_00011_00010_111_00001_0110011; // and x1, x2, x3
        memory[5]  = 32'b0000000_00011_00010_001_00001_0110011; // sll x1, x2, x3
        memory[6]  = 32'b0000000_00011_00010_101_00001_0110011; // srl x1, x2, x3
        memory[7]  = 32'b0100000_00011_00010_101_00001_0110011; // sra x1, x2, x3
        memory[8]  = 32'b0000000_00011_00010_010_00001_0110011; // slt x1, x2, x3
        memory[9]  = 32'b0000000_00011_00010_011_00001_0110011; // sltu x1, x2, x3
        
//(I-type)						       								
        memory[10] = 32'b000000000001_00010_000_00001_0010011; // addi x1, x2, 1
        memory[11] = 32'b000000000001_00010_100_00001_0010011; // xori x1, x2, 1
        memory[12] = 32'b000000000001_00010_110_00001_0010011; // ori x1, x2, 1
        memory[13] = 32'b000000000001_00010_111_00001_0010011; // andi x1, x2, 1
        memory[14] = 32'b000000000001_00010_001_00001_0010011; // slli x1, x2, 1 (shamt) 
        memory[15] = 32'b000000000001_00010_101_00001_0010011; // srli x1, x2, 1 (shamt)
        memory[16] = 32'b010000000001_00010_101_00001_0010011; // srai x1, x2, 1 (shamt)
        memory[17] = 32'b000000000001_00010_010_00001_0010011; // slti x1, x2, 1
        memory[18] = 32'b000000000001_00010_011_00001_0010011; // sltiu x1, x2, 1
//(U-type)
	memory[19] = 32'b000000000001_00010_000_00001_0110111; // lui imm rd 1
        memory[20] = 32'b000000000001_00010_100_00001_0010111; // auipe 
// ********************條件跳轉*********************
// (B-type)
        memory[21] = 32'b0000000_00010_00001_000_00010_1100011; // beq x1, x2, offset
        memory[22] = 32'b0000000_00010_00001_001_00010_1100011; // bne x1, x2, offset
        memory[23] = 32'b0000000_00010_00001_100_00010_1100011; // blt x1, x2, offset
        memory[24] = 32'b0000000_00010_00001_101_00010_1100011; // bge x1, x2, offset
        memory[25] = 32'b0000000_00010_00001_110_00010_1100011; // bltu x1, x2, offset
        memory[26] = 32'b0000000_00010_00001_111_00010_1100011; // bgeu x1, x2, offset
// (J-type)
        memory[27] = 32'b000000000100_00000_110_00001_1101111; // jal x1, offset
        memory[28] = 32'b000000000100_00001_000_00010_1100111; // jalr x2, x1, offset

// ********************reading instru*********************
        memory[29] = 32'b000000000000_00101_010_00100_0000011;  // lw x4, 0(x5)
        memory[30] = 32'b000000000000_00101_000_00100_0000011;  // lb x4, 0(x5)
        memory[31] = 32'b000000000000_00101_001_00100_0000011;  // lh x4, 0(x5)
        memory[32] = 32'b000000000000_00101_100_00100_0000011;  // lbu x4, 0(x5)
        memory[33] = 32'b000000000000_00101_101_00100_0000011;  // lhu x4, 0(x5)
        memory[34] = 32'b0000000_00001_00010_010_00000_0100011; // sw x1, 0(x2)
        memory[35] = 32'b0000000_00001_00010_000_00000_0100011; // sb x1, 0(x2)
        memory[36] = 32'b0000000_00001_00010_001_00000_0100011; // sh x1, 0(x2)

//********************pesudo instr*********************
        memory[37] = 32'b000000000000_00000_000_00000_0010011; // nop (addi x0, x0, 0)
        memory[38] = 32'b000000000000_00001_000_00010_0110011; // mv x2, x1 (add x2, x1, x0)
        memory[39] = 32'b000000000000_00000_000_00001_0010011; // li x1, 0 (addi x1, x0, 0)
        memory[40] = 32'b000000000100_00000_110_00001_1101111; // call (jal x1, offset)
        memory[41] = 32'b000000000000_00001_000_00010_1100111; // ret (jalr x0, x1, 0)


    end
// 共41條指令
    // IF
    always @(*) begin
        instr = memory[addr[17:2]]; // addr[17:2]
	// 2^16 = 65535 
	// 每條指令間隔4bytes +4 > 省略01 ＝ 1 / 00 ＝ 0 / 11 ＝ 3 / 10 ＝ 2 的可能
    end
endmodule

withoutmem/pc.v
`timescale 1ns/100ps

module PC (
    input wire clk,             
    input wire reset,           
    input wire [31:0] next_pc,  
    output reg [31:0] pc         
);

  
    initial begin
        pc = 32'b0;
    end


    always @(posedge clk or posedge reset) begin
        if (reset) begin
            pc <= 32'b0;          
        end else begin
            pc <= next_pc;        
        end
    end

endmodule

cpu.v
`timescale 1ns/100ps
module CPU (
    input wire clk,
    input wire reset
);

    wire [31:0] pc, next_pc, instr, imm;
    wire [31:0] busA, busB, alu_result, mem_data;
    wire [4:0] rs1, rs2, rd;
    wire [1:0] ALUOp;
    wire RegWrite, MemWrite, MemRead, MemToReg, ALUSrc, Branch, Jump, Zero, Less;

    // Program Counter (PC)
    PC pc_reg (
        .clk(clk),
        .reset(reset),
        .next_pc(next_pc),
        .pc(pc)
    );

    // Instruction Memory
    Instr_Mem instr_mem (
        .addr(pc),
        .instr(instr)
    );

    // Instruction Decode (extract fields from instr)
    assign rs1 = instr[19:15];
    assign rs2 = instr[24:20];
    assign rd  = instr[11:7];
    assign imm ={{20{instr[31]}}, instr[31:20]};
//*************************************************
    // Control Unit
    ControlUnit control (
        .opcode(instr[6:0]),
        .funct3(instr[14:12]),
        .funct7(instr[31:25]),
        .RegWrite(RegWrite),
        .MemWrite(MemWrite),
        .MemRead(MemRead),
        .MemToReg(MemToReg),
        .ALUSrc(ALUSrc),
        .Branch(Branch),
        .Jump(Jump),
        .ALUOp(ALUOp)
    );

    // Register File
    register_file reg_file (
        .WrClk(clk),
        .RegWr(RegWrite),
        .Ra(rs1),
        .Rb(rs2),
        .Rw(rd),
        .busW(mem_data), 
        .busA(busA),
        .busB(busB)
    );

    // ALU
 ALU alu (
    .A(busA),
    .B(ALUSrc ? imm : busB),
    .ALUOp(ALUOp),
    .shamt(instr[24:20]),         
    .funct7(instr[31:25]),       
    .Result(alu_result),          
    .Zero(Zero),
    .Less(Less)
);
    // Data Memory
    DataMemory data_mem (
        .clk(clk),
        .MemRead(MemRead),
        .MemWrite(MemWrite),
        .addr(alu_result),
        .write_data(busB),
        .read_data(mem_data)
    );

    // PC Update Logic
    assign next_pc = (Jump) ? alu_result : ((Branch && Zero) ?  (pc + imm)  : (pc + 4));

endmodule

CPU/tbcpu.v
`timescale 1ns/100ps

module CPU_tb;
    reg clk;
    reg reset;


    CPU cpu (
        .clk(clk),
        .reset(reset)
    );


    always #5 clk = ~clk;

    initial begin
 
        clk = 0;
        reset = 1;
        #10;
        reset = 0; 

      
        #500;

  
        $finish;
    end

    initial begin
 
        $dumpfile("CPU_tb.vcd");
        $dumpvars;


        $monitor("Time: %0t, PC: %h, Instr: %h", $time, cpu.pc, cpu.instr);
    end
endmodule

CPU/CPU_tb.vcd
$date
	Sat Sep 28 21:45:38 2024
$end
$version
	Icarus Verilog
$end
$timescale
	100ps
$end
$scope module CPU_tb $end
$var reg 1 ! clk $end
$var reg 1 " reset $end
$scope module cpu $end
$var wire 1 ! clk $end
$var wire 1 " reset $end
$var wire 5 # rs2 [4:0] $end
$var wire 5 $ rs1 [4:0] $end
$var wire 5 % rd [4:0] $end
$var wire 32 & pc [31:0] $end
$var wire 32 ' next_pc [31:0] $end
$var wire 32 ( mem_data [31:0] $end
$var wire 32 ) instr [31:0] $end
$var wire 32 * imm [31:0] $end
$var wire 32 + busB [31:0] $end
$var wire 32 , busA [31:0] $end
$var wire 32 - alu_result [31:0] $end
$var wire 1 . Zero $end
$var wire 1 / RegWrite $end
$var wire 1 0 MemWrite $end
$var wire 1 1 MemToReg $end
$var wire 1 2 MemRead $end
$var wire 1 3 Less $end
$var wire 1 4 Jump $end
$var wire 1 5 Branch $end
$var wire 1 6 ALUSrc $end
$var wire 2 7 ALUOp [1:0] $end
$scope module alu $end
$var wire 32 8 B [31:0] $end
$var wire 3 9 funct3 [2:0] $end
$var wire 7 : funct7 [6:0] $end
$var wire 5 ; shamt [4:0] $end
$var wire 1 . Zero $end
$var wire 2 < ALUOp [1:0] $end
$var wire 32 = A [31:0] $end
$var reg 1 3 Less $end
$var reg 32 > Result [31:0] $end
$upscope $end
$scope module control $end
$var wire 3 ? funct3 [2:0] $end
$var wire 7 @ funct7 [6:0] $end
$var wire 7 A opcode [6:0] $end
$var reg 2 B ALUOp [1:0] $end
$var reg 1 6 ALUSrc $end
$var reg 1 5 Branch $end
$var reg 1 4 Jump $end
$var reg 1 2 MemRead $end
$var reg 1 1 MemToReg $end
$var reg 1 0 MemWrite $end
$var reg 1 / RegWrite $end
$upscope $end
$scope module data_mem $end
$var wire 1 2 MemRead $end
$var wire 1 0 MemWrite $end
$var wire 32 C addr [31:0] $end
$var wire 1 ! clk $end
$var wire 32 D write_data [31:0] $end
$var reg 32 E read_data [31:0] $end
$var integer 32 F i [31:0] $end
$upscope $end
$scope module instr_mem $end
$var wire 32 G addr [31:0] $end
$var reg 32 H instr [31:0] $end
$upscope $end
$scope module pc_reg $end
$var wire 1 ! clk $end
$var wire 32 I next_pc [31:0] $end
$var wire 1 " reset $end
$var reg 32 J pc [31:0] $end
$upscope $end
$scope module reg_file $end
$var wire 5 K Ra [4:0] $end
$var wire 5 L Rb [4:0] $end
$var wire 1 / RegWr $end
$var wire 5 M Rw [4:0] $end
$var wire 1 ! WrClk $end
$var wire 32 N busW [31:0] $end
$var wire 32 O busB [31:0] $end
$var wire 32 P busA [31:0] $end
$var integer 32 Q i [31:0] $end
$upscope $end
$upscope $end
$upscope $end
$enddefinitions $end
#0
$dumpvars
b100000 Q
b0 P
b0 O
bx N
b1 M
b11 L
b10 K
b0 J
b100 I
b1100010000000010110011 H
b0 G
b10000000000000000 F
bx E
b0 D
b0 C
b10 B
b110011 A
b0 @
b0 ?
b0 >
b0 =
b10 <
b11 ;
b0 :
bz 9
b0 8
b10 7
06
05
04
03
02
01
00
1/
1.
b0 -
b0 ,
b0 +
b11 *
b1100010000000010110011 )
bx (
b100 '
b0 &
b1 %
b10 $
b11 #
1"
0!
$end
#50
1!
#100
0!
0"
#150
b1000 '
b1000 I
b100000 :
b100000 @
b10000000011 *
b1000000001100010000000010110011 )
b1000000001100010000000010110011 H
b100 &
b100 G
b100 J
1!
#200
0!
#250
b1100 '
b1100 I
b0 :
b0 @
b100 ?
b11 *
b1100010100000010110011 )
b1100010100000010110011 H
b1000 &
b1000 G
b1000 J
1!
#300
0!
#350
b10000 '
b10000 I
b110 ?
b1100010110000010110011 )
b1100010110000010110011 H
b1100 &
b1100 G
b1100 J
1!
#400
0!
#450
b10100 '
b10100 I
b111 ?
b1100010111000010110011 )
b1100010111000010110011 H
b10000 &
b10000 G
b10000 J
1!
#500
0!
#550
b11000 '
b11000 I
b1 ?
b1100010001000010110011 )
b1100010001000010110011 H
b10100 &
b10100 G
b10100 J
1!
#600
0!
#650
b11100 '
b11100 I
b101 ?
b1100010101000010110011 )
b1100010101000010110011 H
b11000 &
b11000 G
b11000 J
1!
#700
0!
#750
b100000 '
b100000 I
b100000 :
b100000 @
b10000000011 *
b1000000001100010101000010110011 )
b1000000001100010101000010110011 H
b11100 &
b11100 G
b11100 J
1!
#800
0!
#850
b100100 '
b100100 I
b0 :
b0 @
b10 ?
b11 *
b1100010010000010110011 )
b1100010010000010110011 H
b100000 &
b100000 G
b100000 J
1!
#900
0!
#950
b101000 '
b101000 I
b11 ?
b1100010011000010110011 )
b1100010011000010110011 H
b100100 &
b100100 G
b100100 J
1!
#1000
0!
#1050
x.
bx -
bx >
bx C
x3
bx 8
b0 7
b0 <
b0 B
0/
bx +
bx D
bx O
b101100 '
b101100 I
b1 ;
b0 ?
b10011 A
b1 *
b1 #
b1 L
b100010000000010010011 )
b100010000000010010011 H
b101000 &
b101000 G
b101000 J
1!
#1100
0!
#1150
b110000 '
b110000 I
b100 ?
b100010100000010010011 )
b100010100000010010011 H
b101100 &
b101100 G
b101100 J
1!
#1200
0!
#1250
b110100 '
b110100 I
b110 ?
b100010110000010010011 )
b100010110000010010011 H
b110000 &
b110000 G
b110000 J
1!
#1300
0!
#1350
b111000 '
b111000 I
b111 ?
b100010111000010010011 )
b100010111000010010011 H
b110100 &
b110100 G
b110100 J
1!
#1400
0!
#1450
b111100 '
b111100 I
b1 ?
b100010001000010010011 )
b100010001000010010011 H
b111000 &
b111000 G
b111000 J
1!
#1500
0!
#1550
b1000000 '
b1000000 I
b101 ?
b100010101000010010011 )
b100010101000010010011 H
b111100 &
b111100 G
b111100 J
1!
#1600
0!
#1650
b1000100 '
b1000100 I
b100000 :
b100000 @
b10000000001 *
b1000000000100010101000010010011 )
b1000000000100010101000010010011 H
b1000000 &
b1000000 G
b1000000 J
1!
#1700
0!
#1750
b1001000 '
b1001000 I
b0 :
b0 @
b10 ?
b1 *
b100010010000010010011 )
b100010010000010010011 H
b1000100 &
b1000100 G
b1000100 J
1!
#1800
0!
#1850
b1001100 '
b1001100 I
b11 ?
b100010011000010010011 )
b100010011000010010011 H
b1001000 &
b1001000 G
b1001000 J
1!
#1900
0!
#1950
b1010000 '
b1010000 I
b0 ?
b110111 A
b100010000000010110111 )
b100010000000010110111 H
b1001100 &
b1001100 G
b1001100 J
1!
#2000
0!
#2050
b1010100 '
b1010100 I
b100 ?
b10111 A
b100010100000010010111 )
b100010100000010010111 H
b1010000 &
b1010000 G
b1010000 J
1!
#2100
0!
#2150
b0 8
1.
b0 -
b0 >
b0 C
b1 7
b1 <
b1 B
15
b0 +
b0 D
b0 O
bx ,
bx =
bx P
b1010110 '
b1010110 I
b10 ;
b0 ?
b1100011 A
b10 *
b10 %
b10 M
b10 #
b10 L
b1 $
b1 K
b1000001000000101100011 )
b1000001000000101100011 H
b1010100 &
b1010100 G
b1010100 J
1!
#2200
0!
#2250
b1011000 '
b1011000 I
b1010110 &
b1010110 G
b1010110 J
1!
#2300
0!
#2350
b1011010 '
b1011010 I
b1 ?
b1000001001000101100011 )
b1000001001000101100011 H
b1011000 &
b1011000 G
b1011000 J
1!
#2400
0!
#2450
b1011100 '
b1011100 I
b1011010 &
b1011010 G
b1011010 J
1!
#2500
0!
#2550
b1011110 '
b1011110 I
b100 ?
b1000001100000101100011 )
b1000001100000101100011 H
b1011100 &
b1011100 G
b1011100 J
1!
#2600
0!
#2650
b1100000 '
b1100000 I
b1011110 &
b1011110 G
b1011110 J
1!
#2700
0!
#2750
b1100010 '
b1100010 I
b101 ?
b1000001101000101100011 )
b1000001101000101100011 H
b1100000 &
b1100000 G
b1100000 J
1!
#2800
0!
#2850
b1100100 '
b1100100 I
b1100010 &
b1100010 G
b1100010 J
1!
#2900
0!
#2950
b1100110 '
b1100110 I
b110 ?
b1000001110000101100011 )
b1000001110000101100011 H
b1100100 &
b1100100 G
b1100100 J
1!
#3000
0!
#3050
b1101000 '
b1101000 I
b1100110 &
b1100110 G
b1100110 J
1!
#3100
0!
#3150
b1101010 '
b1101010 I
b111 ?
b1000001111000101100011 )
b1000001111000101100011 H
b1101000 &
b1101000 G
b1101000 J
1!
#3200
0!
#3250
b1101100 '
b1101100 I
b1101010 &
b1101010 G
b1101010 J
1!
#3300
0!
#3350
03
14
1/
b0 7
b0 <
b0 B
05
b0 ,
b0 =
b0 P
b0 '
b0 I
b100 ;
b110 ?
b1101111 A
b100 *
b1 %
b1 M
b100 #
b100 L
b0 $
b0 K
b10000000110000011101111 )
b10000000110000011101111 H
b1101100 &
b1101100 G
b1101100 J
1!
#3400
0!
#3450
b100 '
b100 I
b10 7
b10 <
b10 B
04
1/
b11 ;
b0 ?
b110011 A
b11 *
b11 #
b11 L
b10 $
b10 K
b1100010000000010110011 )
b1100010000000010110011 H
b0 &
b0 G
b0 J
1!
#3500
0!
#3550
b1000 '
b1000 I
b100000 :
b100000 @
b10000000011 *
b1000000001100010000000010110011 )
b1000000001100010000000010110011 H
b100 &
b100 G
b100 J
1!
#3600
0!
#3650
b1100 '
b1100 I
b0 :
b0 @
b100 ?
b11 *
b1100010100000010110011 )
b1100010100000010110011 H
b1000 &
b1000 G
b1000 J
1!
#3700
0!
#3750
b10000 '
b10000 I
b110 ?
b1100010110000010110011 )
b1100010110000010110011 H
b1100 &
b1100 G
b1100 J
1!
#3800
0!
#3850
b10100 '
b10100 I
b111 ?
b1100010111000010110011 )
b1100010111000010110011 H
b10000 &
b10000 G
b10000 J
1!
#3900
0!
#3950
b11000 '
b11000 I
b1 ?
b1100010001000010110011 )
b1100010001000010110011 H
b10100 &
b10100 G
b10100 J
1!
#4000
0!
#4050
b11100 '
b11100 I
b101 ?
b1100010101000010110011 )
b1100010101000010110011 H
b11000 &
b11000 G
b11000 J
1!
#4100
0!
#4150
b100000 '
b100000 I
b100000 :
b100000 @
b10000000011 *
b1000000001100010101000010110011 )
b1000000001100010101000010110011 H
b11100 &
b11100 G
b11100 J
1!
#4200
0!
#4250
b100100 '
b100100 I
b0 :
b0 @
b10 ?
b11 *
b1100010010000010110011 )
b1100010010000010110011 H
b100000 &
b100000 G
b100000 J
1!
#4300
0!
#4350
b101000 '
b101000 I
b11 ?
b1100010011000010110011 )
b1100010011000010110011 H
b100100 &
b100100 G
b100100 J
1!
#4400
0!
#4450
x.
bx -
bx >
bx C
x3
bx 8
b0 7
b0 <
b0 B
0/
bx +
bx D
bx O
b101100 '
b101100 I
b1 ;
b0 ?
b10011 A
b1 *
b1 #
b1 L
b100010000000010010011 )
b100010000000010010011 H
b101000 &
b101000 G
b101000 J
1!
#4500
0!
#4550
b110000 '
b110000 I
b100 ?
b100010100000010010011 )
b100010100000010010011 H
b101100 &
b101100 G
b101100 J
1!
#4600
0!
#4650
b110100 '
b110100 I
b110 ?
b100010110000010010011 )
b100010110000010010011 H
b110000 &
b110000 G
b110000 J
1!
#4700
0!
#4750
b111000 '
b111000 I
b111 ?
b100010111000010010011 )
b100010111000010010011 H
b110100 &
b110100 G
b110100 J
1!
#4800
0!
#4850
b111100 '
b111100 I
b1 ?
b100010001000010010011 )
b100010001000010010011 H
b111000 &
b111000 G
b111000 J
1!
#4900
0!
#4950
b1000000 '
b1000000 I
b101 ?
b100010101000010010011 )
b100010101000010010011 H
b111100 &
b111100 G
b111100 J
1!
#5000
0!
#5050
b1000100 '
b1000100 I
b100000 :
b100000 @
b10000000001 *
b1000000000100010101000010010011 )
b1000000000100010101000010010011 H
b1000000 &
b1000000 G
b1000000 J
1!
