mem.v
`timescale 1ns/100ps

module DataMemory (
    input wire clk,                
    input wire MemRead,            
    input wire MemWrite,           
    input wire [31:0] addr,        
    input wire [31:0] write_data,  
    output reg [31:0] read_data    
);

    reg [31:0] memory [0:65535];  
    integer i;
    initial begin
        for (i = 0; i < 65536; i = i + 1) begin
            memory[i] = 32'b0;
        end
    end
    always @(negedge clk) begin
        if (MemWrite) begin
            memory[addr[15:0] >> 2] <= write_data;  
        end
    end
    always @(posedge clk) begin
        if (MemRead) begin
            read_data <= memory[addr[15:0] >> 2];   
        end
    end
endmodule

reg/tb.v
`timescale 1ns/100ps

module DataMemory_tb;
    reg clk;
    reg MemRead;
    reg MemWrite;
    reg [31:0] addr;
    reg [31:0] write_data;
    wire [31:0] read_data;

    // 實例化 DataMemory 模組
    DataMemory uut (
        .clk(clk),
        .MemRead(MemRead),
        .MemWrite(MemWrite),
        .addr(addr),
        .write_data(write_data),
        .read_data(read_data)
    );

    // 時鐘產生
    always #5 clk = ~clk;

    // 初始化信號
    initial begin
        clk = 0;
        MemRead = 0;
        MemWrite = 0;
        addr = 32'b0;
        write_data = 32'b0;

        // 第一個寫入操作
        #10;
        MemWrite = 1;
        addr = 32'd4;          // 地址4
        write_data = 32'd100;  // 寫入100
        #10;
        MemWrite = 0;          // 停止寫入

        // 第二個寫入操作
        #10;
        MemWrite = 1;
        addr = 32'd8;          // 地址8
        write_data = 32'd200;  // 寫入200
        #10;
        MemWrite = 0;          // 停止寫入

        // 第一次讀取操作
        #10;
        MemRead = 1;
        addr = 32'd4;          // 讀取地址4
        #10;
        MemRead = 0;

        // 第二次讀取操作
        #10;
        MemRead = 1;
        addr = 32'd8;          // 讀取地址8
        #10;
        MemRead = 0;

        // 第三次寫入操作
        #10;
        MemWrite = 1;
        addr = 32'd12;         // 地址12
        write_data = 32'd300;  // 寫入300
        #10;
        MemWrite = 0;

        // 第三次讀取操作
        #10;
        MemRead = 1;
        addr = 32'd12;         // 讀取地址12
        #10;
        MemRead = 0;

        // 顯示結果並結束模擬
        #10;
        $finish;
    end

    // 顯示信號變化
    initial begin
        $monitor("Time: %0t | MemWrite: %0b | MemRead: %0b | Addr: %h | Write Data: %h | Read Data: %h",
                 $time, MemWrite, MemRead, addr, write_data, read_data);
    end

    initial begin
        $dumpfile("DataMemory_tb.vcd");
        $dumpvars;
    end
endmodule

dm/DataMemory_tb.vcd
$date
	Sat Oct  5 18:05:46 2024
$end
$version
	Icarus Verilog
$end
$timescale
	100ps
$end
$scope module DataMemory_tb $end
$var wire 32 ! read_data [31:0] $end
$var reg 1 " MemRead $end
$var reg 1 # MemWrite $end
$var reg 32 $ addr [31:0] $end
$var reg 1 % clk $end
$var reg 32 & write_data [31:0] $end
$scope module uut $end
$var wire 1 " MemRead $end
$var wire 1 # MemWrite $end
$var wire 32 ' addr [31:0] $end
$var wire 1 % clk $end
$var wire 32 ( write_data [31:0] $end
$var reg 32 ) read_data [31:0] $end
$var integer 32 * i [31:0] $end
$upscope $end
$upscope $end
$enddefinitions $end
#0
$dumpvars
b10000000000000000 *
bx )
b0 (
b0 '
b0 &
0%
b0 $
0#
0"
bx !
$end
#50
1%
#100
0%
b1100100 &
b1100100 (
b100 $
b100 '
1#
#150
1%
#200
0%
0#
#250
1%
#300
0%
b11001000 &
b11001000 (
b1000 $
b1000 '
1#
#350
1%
#400
0%
0#
#450
1%
#500
0%
b100 $
b100 '
1"
#550
b1100100 !
b1100100 )
1%
#600
0%
0"
#650
1%
#700
0%
b1000 $
b1000 '
1"
#750
b11001000 !
b11001000 )
1%
#800
0%
0"
#850
1%
#900
0%
b100101100 &
b100101100 (
b1100 $
b1100 '
1#
#950
1%
#1000
0%
0#
#1050
1%
#1100
0%
1"
#1150
b100101100 !
b100101100 )
1%
#1200
0%
0"
