mem.v
`timescale 1ns/100ps

module DataMemory (
    input wire clk,                
    input wire MemRead,            
    input wire MemWrite,           
    input wire [31:0] addr,        
    input wire [31:0] write_data,  
    output reg [31:0] read_data    
);

    reg [31:0] memory [0:65535];  
    integer i;
    initial begin
        for (i = 0; i < 65536; i = i + 1) begin
            memory[i] = 32'b0;
        end
    end
    always @(negedge clk) begin
        if (MemWrite) begin
            memory[addr[15:0] >> 2] <= write_data;  
        end
    end
    always @(posedge clk) begin
        if (MemRead) begin
            read_data <= memory[addr[15:0] >> 2];   
        end
    end
endmodule

dm/tbmem.v
`timescale 1ns/100ps

module DataMemory_tb;
    reg clk;
    reg MemRead;
    reg MemWrite;
    reg [31:0] addr;
    reg [31:0] write_data;
    wire [31:0] read_data;


    DataMemory uut (
        .clk(clk),
        .MemRead(MemRead),
        .MemWrite(MemWrite),
        .addr(addr),
        .write_data(write_data),
        .read_data(read_data)
    );


    always #5 clk = ~clk;

    initial begin
        $dumpfile("DM.vcd");
        $dumpvars;

        clk = 0;
        MemRead = 0;
        MemWrite = 0;
        addr = 32'b0;
        write_data = 32'b0;

        // Test 1: write in x0
        #10;
        MemWrite = 1;        
        addr = 32'h00000000; 
        write_data = 32'hDEADBEEF; 
        #10;
        MemWrite = 0;        

        // Test 2: read x0
        #10;
        MemRead = 1;         
        addr = 32'h00000000; 
        #10;
        $display("Test 2: Read Data at Addr 0 = %h", read_data);
        MemRead = 0;      

        // Test 3: write x4
        #10;
        MemWrite = 1;        
        addr = 32'h00000004; 
        write_data = 32'h12345678; 
        #10;
        MemWrite = 0;       

        // Test 4: read x4
        #10;
        MemRead = 1;         
        addr = 32'h00000004;
        #10;
        $display("Test 4: Read Data at Addr 4 = %h", read_data);
        MemRead = 0;         

        // Test 5: read x8
        #10;
        MemRead = 1;        
        addr = 32'h00000008; 
        #10;
        $display("Test 5: Read Data at Addr 8 = %h (should be 0)", read_data);
        MemRead = 0;         

        $finish;
    end
endmodule

dm/DM.vcd
$date
	Sat Sep 28 18:06:37 2024
$end
$version
	Icarus Verilog
$end
$timescale
	100ps
$end
$scope module DataMemory_tb $end
$var wire 32 ! read_data [31:0] $end
$var reg 1 " MemRead $end
$var reg 1 # MemWrite $end
$var reg 32 $ addr [31:0] $end
$var reg 1 % clk $end
$var reg 32 & write_data [31:0] $end
$scope module uut $end
$var wire 1 " MemRead $end
$var wire 1 # MemWrite $end
$var wire 32 ' addr [31:0] $end
$var wire 1 % clk $end
$var wire 32 ( write_data [31:0] $end
$var reg 32 ) read_data [31:0] $end
$var integer 32 * i [31:0] $end
$upscope $end
$upscope $end
$enddefinitions $end
#0
$dumpvars
b10000000000000000 *
bx )
b0 (
b0 '
b0 &
0%
b0 $
0#
0"
bx !
$end
#50
1%
#100
0%
b11011110101011011011111011101111 &
b11011110101011011011111011101111 (
1#
#150
1%
#200
0%
0#
#250
1%
#300
0%
1"
#350
b11011110101011011011111011101111 !
b11011110101011011011111011101111 )
1%
#400
0%
0"
#450
1%
#500
0%
b10010001101000101011001111000 &
b10010001101000101011001111000 (
b100 $
b100 '
1#
#550
1%
#600
0%
0#
#650
1%
#700
0%
1"
#750
b10010001101000101011001111000 !
b10010001101000101011001111000 )
1%
#800
0%
0"
#850
1%
#900
0%
b1000 $
b1000 '
1"
#950
b0 !
b0 )
1%
#1000
0%
0"
