regst.v
`timescale 1ns/100ps

module register_file (
    input wire [4:0] Ra,       // rs1
    input wire [4:0] Rb,       // rs2
    input wire [4:0] Rw,       // rd
    input wire [31:0] busW,    // data write
    input wire RegWr,          // enable
    input wire WrClk,          // clk
    output wire [31:0] busA,   // data read 1
    output wire [31:0] busB,   // data read 2
    output wire [31:0] reg1,   // observe register x1
    output wire [31:0] reg2    // observe register x2
);

    // 32條32位元的寄存器
    reg [31:0] registers [31:0];

    // 讀取寄存器 x0~x31
    assign busA = (Ra == 5'b0) ? 32'b0 : registers[Ra];  // x0 永遠為 0
    assign busB = (Rb == 5'b0) ? 32'b0 : registers[Rb];  // x0 永遠為 0

    // x1 和 x2 的額外輸出端口，用於觀察其值
    assign reg1 = registers[1];
    assign reg2 = registers[2];

    // 在時鐘的下降沿進行寫入操作
    always @(negedge WrClk) begin
        if (RegWr && (Rw != 5'b0)) begin  // x0 無法寫入
            registers[Rw] <= busW;
        end
    end

    // 初始化寄存器為 0
    integer i;
    initial begin
        for (i = 0; i < 32; i = i + 1) begin
            registers[i] = 32'b0;
        end
    end
endmodule

reg+pc+instr/instmem.v
`timescale 1ns/100ps

module Instr_Mem (
    input wire [31:0] addr,  // programming counter addr (motion that should do)
    output reg [31:0] instr  // instr output
);

    reg [31:0] memory [0:65535]; //64k instr = 128kbyte
    // initial (wouldn't change if u don't want to do more)
    initial begin
// ********************整數運算*********************
// opcode rs rs2 rd imm	
//(R-type)
        memory[0]  = 32'b0000000_00011_00010_000_00001_0110011; // add x1, x2, x3
        memory[1]  = 32'b0100000_00011_00010_000_00001_0110011; // sub x1, x2, x3
        memory[2]  = 32'b0000000_00011_00010_100_00001_0110011; // xor x1, x2, x3
        memory[3]  = 32'b0000000_00011_00010_110_00001_0110011; // or x1, x2, x3
        memory[4]  = 32'b0000000_00011_00010_111_00001_0110011; // and x1, x2, x3
        memory[5]  = 32'b0000000_00011_00010_001_00001_0110011; // sll x1, x2, x3
        memory[6]  = 32'b0000000_00011_00010_101_00001_0110011; // srl x1, x2, x3
        memory[7]  = 32'b0100000_00011_00010_101_00001_0110011; // sra x1, x2, x3
        memory[8]  = 32'b0000000_00011_00010_010_00001_0110011; // slt x1, x2, x3
        memory[9]  = 32'b0000000_00011_00010_011_00001_0110011; // sltu x1, x2, x3
        
//(I-type)						       								
        memory[10] = 32'b000000000001_00010_000_00001_0010011; // addi x1, x2, 1
        memory[11] = 32'b000000000001_00010_100_00001_0010011; // xori x1, x2, 1
        memory[12] = 32'b000000000001_00010_110_00001_0010011; // ori x1, x2, 1
        memory[13] = 32'b000000000001_00010_111_00001_0010011; // andi x1, x2, 1
        memory[14] = 32'b000000000001_00010_001_00001_0010011; // slli x1, x2, 1 (shamt) 
        memory[15] = 32'b000000000001_00010_101_00001_0010011; // srli x1, x2, 1 (shamt)
        memory[16] = 32'b010000000001_00010_101_00001_0010011; // srai x1, x2, 1 (shamt)
        memory[17] = 32'b000000000001_00010_010_00001_0010011; // slti x1, x2, 1
        memory[18] = 32'b000000000001_00010_011_00001_0010011; // sltiu x1, x2, 1
//(U-type)
	memory[19] = 32'b000000000001_00010_000_00001_0110111; // lui imm rd 1
        memory[20] = 32'b000000000001_00010_100_00001_0010111; // auipe 
// ********************條件跳轉*********************
// (B-type)
        memory[21] = 32'b0000000_00010_00001_000_00010_1100011; // beq x1, x2, offset
        memory[22] = 32'b0000000_00010_00001_001_00010_1100011; // bne x1, x2, offset
        memory[23] = 32'b0000000_00010_00001_100_00010_1100011; // blt x1, x2, offset
        memory[24] = 32'b0000000_00010_00001_101_00010_1100011; // bge x1, x2, offset
        memory[25] = 32'b0000000_00010_00001_110_00010_1100011; // bltu x1, x2, offset
        memory[26] = 32'b0000000_00010_00001_111_00010_1100011; // bgeu x1, x2, offset
// (J-type)
        memory[27] = 32'b000000000100_00000_110_00001_1101111; // jal x1, offset
        memory[28] = 32'b000000000100_00001_000_00010_1100111; // jalr x2, x1, offset

// ********************reading instru*********************
        memory[29] = 32'b000000000000_00101_010_00100_0000011;  // lw x4, 0(x5)
        memory[30] = 32'b000000000000_00101_000_00100_0000011;  // lb x4, 0(x5)
        memory[31] = 32'b000000000000_00101_001_00100_0000011;  // lh x4, 0(x5)
        memory[32] = 32'b000000000000_00101_100_00100_0000011;  // lbu x4, 0(x5)
        memory[33] = 32'b000000000000_00101_101_00100_0000011;  // lhu x4, 0(x5)
        memory[34] = 32'b0000000_00001_00010_010_00000_0100011; // sw x1, 0(x2)
        memory[35] = 32'b0000000_00001_00010_000_00000_0100011; // sb x1, 0(x2)
        memory[36] = 32'b0000000_00001_00010_001_00000_0100011; // sh x1, 0(x2)

//********************pesudo instr*********************
        memory[37] = 32'b000000000000_00000_000_00000_0010011; // nop (addi x0, x0, 0)
        memory[38] = 32'b000000000000_00001_000_00010_0110011; // mv x2, x1 (add x2, x1, x0)
        memory[39] = 32'b000000000000_00000_000_00001_0010011; // li x1, 0 (addi x1, x0, 0)
        memory[40] = 32'b000000000100_00000_110_00001_1101111; // call (jal x1, offset)
        memory[41] = 32'b000000000000_00001_000_00010_1100111; // ret (jalr x0, x1, 0)


    end
// 共41條指令
    // IF
    always @(*) begin
        instr = memory[addr[17:2]]; // addr[17:2]
	// 2^16 = 65535 
	// 每條指令間隔4bytes +4 > 省略01 ＝ 1 / 00 ＝ 0 / 11 ＝ 3 / 10 ＝ 2 的可能
    end
endmodule

withoutmem/pc.v
`timescale 1ns/100ps

module PC (
    input wire clk,             
    input wire reset,           
    input wire [31:0] next_pc,  
    output reg [31:0] pc         
);

  
    initial begin
        pc = 32'b0;
    end


    always @(posedge clk or posedge reset) begin
        if (reset) begin
            pc <= 32'b0;          
        end else begin
            pc <= next_pc;        
        end
    end

endmodule

reg+pc+instr/cpupart.v
`timescale 1ns/100ps

module CPU (
    input wire clk,
    input wire reset
);

    wire [31:0] pc, next_pc, instr, busA, busB;
    wire [4:0] rs1, rs2, rd;

    // Program Counter (PC)
    PC pc_reg (
        .clk(clk),
        .reset(reset),
        .next_pc(next_pc),
        .pc(pc)
    );

    // Instruction Memory
    Instr_Mem instr_mem (
        .addr(pc),
        .instr(instr)
    );

    // Extract fields from instruction
    assign rs1 = instr[19:15];
    assign rs2 = instr[24:20];
    assign rd  = instr[11:7];

    // Register File
    register_file reg_file (
        .Ra(rs1),
        .Rb(rs2),
        .Rw(rd),
        .busW(32'd0),      // 暫時設為0，無寫入操作
        .RegWr(1'b0),      // 暫時設為0，無寫入操作
        .WrClk(clk),
        .busA(busA),
        .busB(busB)
    );

    // 簡單的PC更新邏輯
    assign next_pc = pc + 4; // PC每次加4以擷取下一條指令

endmodule

reg+pc+instr/tb.v
`timescale 1ns/100ps

module CPU_tb;
    reg clk;
    reg reset;
    wire [31:0] pc, instr, busA, busB;
    
    // Instantiate CPU
    CPU cpu (
        .clk(clk),
        .reset(reset)
    );

    // Monitor Signals
    assign pc = cpu.pc_reg.pc;
    assign instr = cpu.instr_mem.instr;
    assign busA = cpu.reg_file.busA;
    assign busB = cpu.reg_file.busB;

    // Clock Generation
    always #5 clk = ~clk;

    initial begin
        // Initialize signals
        clk = 0;
        reset = 1;
        #10;
        
        reset = 0;  // release reset

        // Test with multiple clock cycles
        #800;  // Adjust time as needed to cover all instructions
        $finish;
    end

    // Monitor output at each clock cycle
    initial begin
        $monitor("Time: %0t | PC: %h | Instr: %b | rs1 Data: %h | rs2 Data: %h", 
                 $time, pc, instr, busA, busB);
    end

    initial begin
        $dumpfile("cpu_tb.vcd");
        $dumpvars;
    end
endmodule

reg+pc+instr/cpu_tb.vcd
$date
	Sat Oct  5 20:40:20 2024
$end
$version
	Icarus Verilog
$end
$timescale
	100ps
$end
$scope module CPU_tb $end
$var wire 32 ! busA [31:0] $end
$var wire 32 " busB [31:0] $end
$var wire 32 # instr [31:0] $end
$var wire 32 $ pc [31:0] $end
$var reg 1 % clk $end
$var reg 1 & reset $end
$scope module cpu $end
$var wire 1 % clk $end
$var wire 1 & reset $end
$var wire 5 ' rs2 [4:0] $end
$var wire 5 ( rs1 [4:0] $end
$var wire 5 ) rd [4:0] $end
$var wire 32 * pc [31:0] $end
$var wire 32 + next_pc [31:0] $end
$var wire 32 , instr [31:0] $end
$var wire 32 - busB [31:0] $end
$var wire 32 . busA [31:0] $end
$scope module instr_mem $end
$var wire 32 / addr [31:0] $end
$var reg 32 0 instr [31:0] $end
$upscope $end
$scope module pc_reg $end
$var wire 1 % clk $end
$var wire 32 1 next_pc [31:0] $end
$var wire 1 & reset $end
$var reg 32 2 pc [31:0] $end
$upscope $end
$scope module reg_file $end
$var wire 5 3 Ra [4:0] $end
$var wire 5 4 Rb [4:0] $end
$var wire 1 5 RegWr $end
$var wire 5 6 Rw [4:0] $end
$var wire 1 % WrClk $end
$var wire 32 7 busW [31:0] $end
$var wire 32 8 reg1 [31:0] $end
$var wire 32 9 reg2 [31:0] $end
$var wire 32 : busB [31:0] $end
$var wire 32 ; busA [31:0] $end
$var integer 32 < i [31:0] $end
$upscope $end
$upscope $end
$upscope $end
$enddefinitions $end
#0
$dumpvars
b100000 <
b0 ;
b0 :
b0 9
b0 8
b0 7
b1 6
05
b11 4
b10 3
b0 2
b100 1
b1100010000000010110011 0
b0 /
b0 .
b0 -
b1100010000000010110011 ,
b100 +
b0 *
b1 )
b10 (
b11 '
1&
0%
b0 $
b1100010000000010110011 #
b0 "
b0 !
$end
#50
1%
#100
0%
0&
#150
b1000000001100010000000010110011 #
b1000000001100010000000010110011 ,
b1000000001100010000000010110011 0
b1000 +
b1000 1
b100 $
b100 *
b100 /
b100 2
1%
#200
0%
#250
b1100010100000010110011 #
b1100010100000010110011 ,
b1100010100000010110011 0
b1100 +
b1100 1
b1000 $
b1000 *
b1000 /
b1000 2
1%
#300
0%
#350
b1100010110000010110011 #
b1100010110000010110011 ,
b1100010110000010110011 0
b10000 +
b10000 1
b1100 $
b1100 *
b1100 /
b1100 2
1%
#400
0%
#450
b1100010111000010110011 #
b1100010111000010110011 ,
b1100010111000010110011 0
b10100 +
b10100 1
b10000 $
b10000 *
b10000 /
b10000 2
1%
#500
0%
#550
b1100010001000010110011 #
b1100010001000010110011 ,
b1100010001000010110011 0
b11000 +
b11000 1
b10100 $
b10100 *
b10100 /
b10100 2
1%
#600
0%
#650
b1100010101000010110011 #
b1100010101000010110011 ,
b1100010101000010110011 0
b11100 +
b11100 1
b11000 $
b11000 *
b11000 /
b11000 2
1%
#700
0%
#750
b1000000001100010101000010110011 #
b1000000001100010101000010110011 ,
b1000000001100010101000010110011 0
b100000 +
b100000 1
b11100 $
b11100 *
b11100 /
b11100 2
1%
#800
0%
#850
b1100010010000010110011 #
b1100010010000010110011 ,
b1100010010000010110011 0
b100100 +
b100100 1
b100000 $
b100000 *
b100000 /
b100000 2
1%
#900
0%
#950
b1100010011000010110011 #
b1100010011000010110011 ,
b1100010011000010110011 0
b101000 +
b101000 1
b100100 $
b100100 *
b100100 /
b100100 2
1%
#1000
0%
#1050
b1 '
b1 4
b100010000000010010011 #
b100010000000010010011 ,
b100010000000010010011 0
b101100 +
b101100 1
b101000 $
b101000 *
b101000 /
b101000 2
1%
#1100
0%
#1150
b100010100000010010011 #
b100010100000010010011 ,
b100010100000010010011 0
b110000 +
b110000 1
b101100 $
b101100 *
b101100 /
b101100 2
1%
#1200
0%
#1250
b100010110000010010011 #
b100010110000010010011 ,
b100010110000010010011 0
b110100 +
b110100 1
b110000 $
b110000 *
b110000 /
b110000 2
1%
#1300
0%
#1350
b100010111000010010011 #
b100010111000010010011 ,
b100010111000010010011 0
b111000 +
b111000 1
b110100 $
b110100 *
b110100 /
b110100 2
1%
#1400
0%
#1450
b100010001000010010011 #
b100010001000010010011 ,
b100010001000010010011 0
b111100 +
b111100 1
b111000 $
b111000 *
b111000 /
b111000 2
1%
#1500
0%
#1550
b100010101000010010011 #
b100010101000010010011 ,
b100010101000010010011 0
b1000000 +
b1000000 1
b111100 $
b111100 *
b111100 /
b111100 2
1%
#1600
0%
#1650
b1000000000100010101000010010011 #
b1000000000100010101000010010011 ,
b1000000000100010101000010010011 0
b1000100 +
b1000100 1
b1000000 $
b1000000 *
b1000000 /
b1000000 2
1%
#1700
0%
#1750
b100010010000010010011 #
b100010010000010010011 ,
b100010010000010010011 0
b1001000 +
b1001000 1
b1000100 $
b1000100 *
b1000100 /
b1000100 2
1%
#1800
0%
#1850
b100010011000010010011 #
b100010011000010010011 ,
b100010011000010010011 0
b1001100 +
b1001100 1
b1001000 $
b1001000 *
b1001000 /
b1001000 2
1%
#1900
0%
#1950
b100010000000010110111 #
b100010000000010110111 ,
b100010000000010110111 0
b1010000 +
b1010000 1
b1001100 $
b1001100 *
b1001100 /
b1001100 2
1%
#2000
0%
#2050
b100010100000010010111 #
b100010100000010010111 ,
b100010100000010010111 0
b1010100 +
b1010100 1
b1010000 $
b1010000 *
b1010000 /
b1010000 2
1%
#2100
0%
#2150
b10 )
b10 6
b10 '
b10 4
b1 (
b1 3
b1000001000000101100011 #
b1000001000000101100011 ,
b1000001000000101100011 0
b1011000 +
b1011000 1
b1010100 $
b1010100 *
b1010100 /
b1010100 2
1%
#2200
0%
#2250
b1000001001000101100011 #
b1000001001000101100011 ,
b1000001001000101100011 0
b1011100 +
b1011100 1
b1011000 $
b1011000 *
b1011000 /
b1011000 2
1%
#2300
0%
#2350
b1000001100000101100011 #
b1000001100000101100011 ,
b1000001100000101100011 0
b1100000 +
b1100000 1
b1011100 $
b1011100 *
b1011100 /
b1011100 2
1%
#2400
0%
#2450
b1000001101000101100011 #
b1000001101000101100011 ,
b1000001101000101100011 0
b1100100 +
b1100100 1
b1100000 $
b1100000 *
b1100000 /
b1100000 2
1%
#2500
0%
#2550
b1000001110000101100011 #
b1000001110000101100011 ,
b1000001110000101100011 0
b1101000 +
b1101000 1
b1100100 $
b1100100 *
b1100100 /
b1100100 2
1%
#2600
0%
#2650
b1000001111000101100011 #
b1000001111000101100011 ,
b1000001111000101100011 0
b1101100 +
b1101100 1
b1101000 $
b1101000 *
b1101000 /
b1101000 2
1%
#2700
0%
#2750
b1 )
b1 6
b100 '
b100 4
b0 (
b0 3
b10000000110000011101111 #
b10000000110000011101111 ,
b10000000110000011101111 0
b1110000 +
b1110000 1
b1101100 $
b1101100 *
b1101100 /
b1101100 2
1%
#2800
0%
#2850
b10 )
b10 6
b1 (
b1 3
b10000001000000101100111 #
b10000001000000101100111 ,
b10000001000000101100111 0
b1110100 +
b1110100 1
b1110000 $
b1110000 *
b1110000 /
b1110000 2
1%
#2900
0%
#2950
b100 )
b100 6
b0 '
b0 4
b101 (
b101 3
b101010001000000011 #
b101010001000000011 ,
b101010001000000011 0
b1111000 +
b1111000 1
b1110100 $
b1110100 *
b1110100 /
b1110100 2
1%
#3000
0%
#3050
b101000001000000011 #
b101000001000000011 ,
b101000001000000011 0
b1111100 +
b1111100 1
b1111000 $
b1111000 *
b1111000 /
b1111000 2
1%
#3100
0%
#3150
b101001001000000011 #
b101001001000000011 ,
b101001001000000011 0
b10000000 +
b10000000 1
b1111100 $
b1111100 *
b1111100 /
b1111100 2
1%
#3200
0%
#3250
b101100001000000011 #
b101100001000000011 ,
b101100001000000011 0
b10000100 +
b10000100 1
b10000000 $
b10000000 *
b10000000 /
b10000000 2
1%
#3300
0%
#3350
b101101001000000011 #
b101101001000000011 ,
b101101001000000011 0
b10001000 +
b10001000 1
b10000100 $
b10000100 *
b10000100 /
b10000100 2
1%
#3400
0%
#3450
b0 )
b0 6
b1 '
b1 4
b10 (
b10 3
b100010010000000100011 #
b100010010000000100011 ,
b100010010000000100011 0
b10001100 +
b10001100 1
b10001000 $
b10001000 *
b10001000 /
b10001000 2
1%
#3500
0%
#3550
b100010000000000100011 #
b100010000000000100011 ,
b100010000000000100011 0
b10010000 +
b10010000 1
b10001100 $
b10001100 *
b10001100 /
b10001100 2
1%
#3600
0%
#3650
b100010001000000100011 #
b100010001000000100011 ,
b100010001000000100011 0
b10010100 +
b10010100 1
b10010000 $
b10010000 *
b10010000 /
b10010000 2
1%
#3700
0%
#3750
b0 '
b0 4
b0 (
b0 3
b10011 #
b10011 ,
b10011 0
b10011000 +
b10011000 1
b10010100 $
b10010100 *
b10010100 /
b10010100 2
1%
#3800
0%
#3850
b10 )
b10 6
b1 (
b1 3
b1000000100110011 #
b1000000100110011 ,
b1000000100110011 0
b10011100 +
b10011100 1
b10011000 $
b10011000 *
b10011000 /
b10011000 2
1%
#3900
0%
#3950
b1 )
b1 6
b0 (
b0 3
b10010011 #
b10010011 ,
b10010011 0
b10100000 +
b10100000 1
b10011100 $
b10011100 *
b10011100 /
b10011100 2
1%
#4000
0%
#4050
b100 '
b100 4
b10000000110000011101111 #
b10000000110000011101111 ,
b10000000110000011101111 0
b10100100 +
b10100100 1
b10100000 $
b10100000 *
b10100000 /
b10100000 2
1%
#4100
0%
#4150
b10 )
b10 6
b0 '
b0 4
b1 (
b1 3
b1000000101100111 #
b1000000101100111 ,
b1000000101100111 0
b10101000 +
b10101000 1
b10100100 $
b10100100 *
b10100100 /
b10100100 2
1%
#4200
0%
#4250
bx "
bx -
bx :
bx !
bx .
bx ;
bx )
bx 6
bx '
bx 4
bx (
bx 3
bx #
bx ,
bx 0
b10101100 +
b10101100 1
b10101000 $
b10101000 *
b10101000 /
b10101000 2
1%
#4300
0%
#4350
b10110000 +
b10110000 1
b10101100 $
b10101100 *
b10101100 /
b10101100 2
1%
#4400
0%
#4450
b10110100 +
b10110100 1
b10110000 $
b10110000 *
b10110000 /
b10110000 2
1%
#4500
0%
#4550
b10111000 +
b10111000 1
b10110100 $
b10110100 *
b10110100 /
b10110100 2
1%
#4600
0%
#4650
b10111100 +
b10111100 1
b10111000 $
b10111000 *
b10111000 /
b10111000 2
1%
#4700
0%
#4750
b11000000 +
b11000000 1
b10111100 $
b10111100 *
b10111100 /
b10111100 2
1%
#4800
0%
#4850
b11000100 +
b11000100 1
b11000000 $
b11000000 *
b11000000 /
b11000000 2
1%
#4900
0%
#4950
b11001000 +
b11001000 1
b11000100 $
b11000100 *
b11000100 /
b11000100 2
1%
#5000
0%
#5050
b11001100 +
b11001100 1
b11001000 $
b11001000 *
b11001000 /
b11001000 2
1%
#5100
0%
#5150
b11010000 +
b11010000 1
b11001100 $
b11001100 *
b11001100 /
b11001100 2
1%
#5200
0%
#5250
b11010100 +
b11010100 1
b11010000 $
b11010000 *
b11010000 /
b11010000 2
1%
#5300
0%
#5350
b11011000 +
b11011000 1
b11010100 $
b11010100 *
b11010100 /
b11010100 2
1%
#5400
0%
#5450
b11011100 +
b11011100 1
b11011000 $
b11011000 *
b11011000 /
b11011000 2
1%
#5500
0%
#5550
b11100000 +
b11100000 1
b11011100 $
b11011100 *
b11011100 /
b11011100 2
1%
#5600
0%
#5650
b11100100 +
b11100100 1
b11100000 $
b11100000 *
b11100000 /
b11100000 2
1%
#5700
0%
#5750
b11101000 +
b11101000 1
b11100100 $
b11100100 *
b11100100 /
b11100100 2
1%
#5800
0%
#5850
b11101100 +
b11101100 1
b11101000 $
b11101000 *
b11101000 /
b11101000 2
1%
#5900
0%
#5950
b11110000 +
b11110000 1
b11101100 $
b11101100 *
b11101100 /
b11101100 2
1%
#6000
0%
#6050
b11110100 +
b11110100 1
b11110000 $
b11110000 *
b11110000 /
b11110000 2
1%
#6100
0%
#6150
b11111000 +
b11111000 1
b11110100 $
b11110100 *
b11110100 /
b11110100 2
1%
#6200
0%
#6250
b11111100 +
b11111100 1
b11111000 $
b11111000 *
b11111000 /
b11111000 2
1%
#6300
0%
#6350
b100000000 +
b100000000 1
b11111100 $
b11111100 *
b11111100 /
b11111100 2
1%
#6400
0%
#6450
b100000100 +
b100000100 1
b100000000 $
b100000000 *
b100000000 /
b100000000 2
1%
#6500
0%
#6550
b100001000 +
b100001000 1
b100000100 $
b100000100 *
b100000100 /
b100000100 2
1%
#6600
0%
#6650
b100001100 +
b100001100 1
b100001000 $
b100001000 *
b100001000 /
b100001000 2
1%
#6700
0%
#6750
b100010000 +
b100010000 1
b100001100 $
b100001100 *
b100001100 /
b100001100 2
1%
#6800
0%
#6850
b100010100 +
b100010100 1
b100010000 $
b100010000 *
b100010000 /
b100010000 2
1%
#6900
0%
#6950
b100011000 +
b100011000 1
b100010100 $
b100010100 *
b100010100 /
b100010100 2
1%
#7000
0%
#7050
b100011100 +
b100011100 1
b100011000 $
b100011000 *
b100011000 /
b100011000 2
1%
#7100
0%
#7150
b100100000 +
b100100000 1
b100011100 $
b100011100 *
b100011100 /
b100011100 2
1%
#7200
0%
#7250
b100100100 +
b100100100 1
b100100000 $
b100100000 *
b100100000 /
b100100000 2
1%
#7300
0%
#7350
b100101000 +
b100101000 1
b100100100 $
b100100100 *
b100100100 /
b100100100 2
1%
#7400
0%
#7450
b100101100 +
b100101100 1
b100101000 $
b100101000 *
b100101000 /
b100101000 2
1%
#7500
0%
#7550
b100110000 +
b100110000 1
b100101100 $
b100101100 *
b100101100 /
b100101100 2
1%
#7600
0%
#7650
b100110100 +
b100110100 1
b100110000 $
b100110000 *
b100110000 /
b100110000 2
1%
#7700
0%
#7750
b100111000 +
b100111000 1
b100110100 $
b100110100 *
b100110100 /
b100110100 2
1%
#7800
0%
#7850
b100111100 +
b100111100 1
b100111000 $
b100111000 *
b100111000 /
b100111000 2
1%
#7900
0%
#7950
b101000000 +
b101000000 1
b100111100 $
b100111100 *
b100111100 /
b100111100 2
1%
#8000
0%
#8050
b101000100 +
b101000100 1
b101000000 $
b101000000 *
b101000000 /
b101000000 2
1%
