regst.v
`timescale 1ns/100ps


module register_file (
    input wire [4:0] Ra,       //r1
    input wire [4:0] Rb,       //r2
    input wire [4:0] Rw,       // rd
    input wire [31:0] busW,    // data write 1
    input wire RegWr,          // enable
    input wire WrClk,          // clk
    output wire [31:0] busA,   // data read 1
    output wire [31:0] busB    // data read 2
);

    // 32條32位元的reg
    reg [31:0] registers [31:0];

    // 讀取reg x0~x31? (使用條件運算子 a = (b)?c:d >> if b = 1 a = c / b = 0 a = d)
    assign busA = (Ra == 5'b0) ? 32'b0 : registers[Ra];  // x0常數限制
    assign busB = (Rb == 5'b0) ? 32'b0 : registers[Rb];  // x0常數限制

    // 寫入於下降寫入
    always @(negedge WrClk) begin
        if (RegWr && Rw ) begin  
            registers[Rw] <= busW;
        end
    end


    // 初始化寄存器为0
    integer i;
    initial begin
        for (i = 0; i < 32; i = i + 1) begin
            registers[i] = 32'b0;
        end
    end
endmodule

reg/tb_regst.v
`timescale 1ns/100ps
module testbench;

    reg [4:0] Ra, Rb, Rw;
    reg [31:0] busW;
    reg RegWr;
    reg WrClk;
    wire [31:0] busA, busB;

   
    register_file rf (
        .Ra(Ra),
        .Rb(Rb),
        .Rw(Rw),
        .busW(busW),
        .RegWr(RegWr),
        .WrClk(WrClk),
        .busA(busA),
        .busB(busB)
    );


    always #5 WrClk = ~WrClk;
    initial begin 
		$dumpfile("regst.vcd");
 		$dumpvars;
 		#180
 		$finish;
 		end
    initial begin
 	   
        WrClk = 0;
        RegWr = 0; //enable
        Ra = 0; //rs1
        Rb = 0; //rs2
        Rw = 0; //rd
        busW = 0;

        // write x1
        #10 RegWr = 1; Rw = 5'b00001; busW = 32'b01010010101101010010101101010010;
        //$display ("busw = 32'hDEADBEEF = %b" , busw);
        // write x2
        #10 Rw = 5'b00010; busW = 32'b01011011101101011010101111010110;
	//$display ("busw = 32'hCAFEBABE = %b" , busw);
        // read
        #10 RegWr = 0; Ra = 5'b00001; Rb = 5'b00010; busW = 32'b11111111101101011010101111010110;

        // write x0
        #10 RegWr = 1; Rw = 5'b00000; busW = 32'b0101101110100101001000001001110;

        // check x0 
        #10 Ra = 5'b00000; Rb = 5'b00001;
	// write x4 + check
        #10 RegWr = 1; Rw = 5'b00100; busW = 32'b01010010101101010010101101010010; Ra = 5'b00101; Rb = 5'b00010;
        //$display ("busw = 32'hDEADBEEF = %b" , busw);
        // write x5 + check
        #10 RegWr = 1; Rw = 5'b00101; busW = 32'b01010010101101010010101101010010; Ra = 5'b00100; Rb = 5'b00101;
        //$display ("busw = 32'hDEADBEEF = %b" , busw);
         // write x10  + check
        #10 RegWr = 1; Rw = 5'b01010; busW = 32'b01010010101101010010101101010010;  Ra = 5'b00101; Rb = 5'b01010;
         // write x30 + check
        #10 RegWr = 1; Rw = 5'b11101; busW = 32'b01010010101101010010101101010010; Ra = 5'b11101; Rb = 5'b01010;
        // write x12
        #10 RegWr = 1; Rw = 5'b01100; busW = 32'b01010010101101010010101101010010; Ra = 5'b11101; Rb = 5'b01100;
        #20 $finish;
    end
endmodule

reg/regst.vcd
$date
	Sat Sep 28 17:33:06 2024
$end
$version
	Icarus Verilog
$end
$timescale
	100ps
$end
$scope module testbench $end
$var wire 32 ! busB [31:0] $end
$var wire 32 " busA [31:0] $end
$var reg 5 # Ra [4:0] $end
$var reg 5 $ Rb [4:0] $end
$var reg 1 % RegWr $end
$var reg 5 & Rw [4:0] $end
$var reg 1 ' WrClk $end
$var reg 32 ( busW [31:0] $end
$scope module rf $end
$var wire 5 ) Ra [4:0] $end
$var wire 5 * Rb [4:0] $end
$var wire 1 % RegWr $end
$var wire 5 + Rw [4:0] $end
$var wire 1 ' WrClk $end
$var wire 32 , busW [31:0] $end
$var wire 32 - busB [31:0] $end
$var wire 32 . busA [31:0] $end
$var integer 32 / i [31:0] $end
$upscope $end
$upscope $end
$enddefinitions $end
#0
$dumpvars
b100000 /
b0 .
b0 -
b0 ,
b0 +
b0 *
b0 )
b0 (
0'
b0 &
0%
b0 $
b0 #
b0 "
b0 !
$end
#50
1'
#100
0'
b1010010101101010010101101010010 (
b1010010101101010010101101010010 ,
b1 &
b1 +
1%
#150
1'
#200
0'
b1011011101101011010101111010110 (
b1011011101101011010101111010110 ,
b10 &
b10 +
#250
1'
#300
b1011011101101011010101111010110 !
b1011011101101011010101111010110 -
b1010010101101010010101101010010 "
b1010010101101010010101101010010 .
0'
b11111111101101011010101111010110 (
b11111111101101011010101111010110 ,
b10 $
b10 *
b1 #
b1 )
0%
#350
1'
#400
0'
b101101110100101001000001001110 (
b101101110100101001000001001110 ,
b0 &
b0 +
1%
#450
1'
#500
b1010010101101010010101101010010 !
b1010010101101010010101101010010 -
b0 "
b0 .
0'
b1 $
b1 *
b0 #
b0 )
#550
1'
#600
b1011011101101011010101111010110 !
b1011011101101011010101111010110 -
0'
b10 $
b10 *
b101 #
b101 )
b1010010101101010010101101010010 (
b1010010101101010010101101010010 ,
b100 &
b100 +
#650
1'
#700
b1010010101101010010101101010010 !
b1010010101101010010101101010010 -
b1010010101101010010101101010010 "
b1010010101101010010101101010010 .
0'
b101 $
b101 *
b100 #
b100 )
b101 &
b101 +
#750
1'
#800
b1010010101101010010101101010010 !
b1010010101101010010101101010010 -
0'
b1010 $
b1010 *
b101 #
b101 )
b1010 &
b1010 +
#850
1'
#900
b1010010101101010010101101010010 "
b1010010101101010010101101010010 .
0'
b11101 #
b11101 )
b11101 &
b11101 +
#950
1'
#1000
b1010010101101010010101101010010 !
b1010010101101010010101101010010 -
0'
b1100 $
b1100 *
b1100 &
b1100 +
