decoder.v
`timescale 1ns/100ps

module Decoder(
    input [31:0] instr,            // 输入的32位指令
    output reg [4:0] rs1,           // 源寄存器1 (rs1)
    output reg [4:0] rs2,           // 源寄存器2 (rs2)
    output reg [4:0] rd,            // 目标寄存器 (rd)
    output reg [2:0] funct3,        // 功能码 (funct3)
    output reg [6:0] funct7,        // 功能码 (funct7)
    output reg [6:0] opcode,        // 操作码 (opcode)
    output reg [31:0] imm,          // 立即数 (imm)
    output reg [4:0] shamt,         // 移位量 (shamt)

    // 控制信号输出
    output reg RegWrite,            // 寄存器写使能
    output reg MemRead,             // 内存读使能
    output reg MemWrite,            // 内存写使能
    output reg MemtoReg,            // 内存数据写入寄存器
    output reg ALUSrc,              // ALU输入来源（立即数或寄存器）
    output reg Branch,              // 跳转信号
    output reg [1:0] ALUOp          // ALU操作码
);

    always @(*) begin
        // 解析指令字段
        opcode = instr[6:0];       // opcode 在指令的第[6:0]位
        rd     = instr[11:7];      // 目标寄存器rd 在第[11:7]位
        funct3 = instr[14:12];     // 功能码funct3 在第[14:12]位
        rs1    = instr[19:15];     // 源寄存器1 rs1 在第[19:15]位
        rs2    = instr[24:20];     // 源寄存器2 rs2 在第[24:20]位
        funct7 = instr[31:25];     // 功能码funct7 在第[31:25]位

        // 默认 shamt 和 立即数
        shamt = 5'b0;
        imm = 32'b0;

        // 默认控制信号
        RegWrite = 0;
        MemRead = 0;
        MemWrite = 0;
        MemtoReg = 0;
        ALUSrc = 0;
        Branch = 0;
        ALUOp = 2'b00;

        // 解码器中的指令分类
        case(opcode)
            7'b0110011: begin  // R-Type 指令 (add, sub, xor, and, or, sll, srl, sra, slt, sltu)
                RegWrite = 1;
                ALUSrc = 0;    // ALU 的输入来自寄存器
                MemtoReg = 0;
                MemRead = 0;
                MemWrite = 0;
                Branch = 0;
                ALUOp = 2'b10; // 生成ALU操作码
            end
            7'b0010011: begin  // I-Type 算术指令 (addi, xori, andi, ori, slti, sltiu)
                RegWrite = 1;
                ALUSrc = 1;    // ALU 的输入来自立即数
                MemtoReg = 0;
                MemRead = 0;
                MemWrite = 0;
                Branch = 0;
                ALUOp = 2'b11; // 立即数操作
                imm = {{20{instr[31]}}, instr[31:20]};  // I-Type 的立即数
            end
            7'b0010011: begin  // I-Type 移位指令 (slli, srli, srai)
                if (funct3 == 3'b001 || funct3 == 3'b101) begin
                    RegWrite = 1;
                    ALUSrc = 1;    // ALU 的输入来自 shamt
                    MemtoReg = 0;
                    MemRead = 0;
                    MemWrite = 0;
                    Branch = 0;
                    ALUOp = 2'b11; // 移位操作
                    shamt = instr[24:20]; // 移位量 shamt
                end else begin
                    // 非移位的I-type指令（如 addi, ori 等）
                    imm = {{20{instr[31]}}, instr[31:20]};
                end
            end
            7'b0000011: begin  // I-Type 负载指令 (lw, lb, lh, lbu, lhu)
                RegWrite = 1;
                ALUSrc = 1;    // ALU 的输入来自立即数（地址偏移量）
                MemtoReg = 1;  // 内存数据写回寄存器
                MemRead = 1;
                MemWrite = 0;
                Branch = 0;
                ALUOp = 2'b00; // 生成地址
                imm = {{20{instr[31]}}, instr[31:20]};  // I-Type 的立即数
            end
            7'b0100011: begin  // S-Type 存储指令 (sw, sb, sh)
                RegWrite = 0;
                ALUSrc = 1;    // ALU 的输入来自立即数（地址偏移量）
                MemtoReg = 0;
                MemRead = 0;
                MemWrite = 1;
                Branch = 0;
                ALUOp = 2'b00; // 生成地址
                imm = {{20{instr[31]}}, instr[31:25], instr[11:7]};  // S-Type 的立即数
            end
            7'b1100011: begin  // B-Type 分支跳转指令 (beq, bne, blt, bge, bltu, bgeu)
                RegWrite = 0;
                ALUSrc = 0;    // ALU 的输入来自寄存器
                MemtoReg = 0;
                MemRead = 0;
                MemWrite = 0;
                Branch = 1;    // 启用分支跳转
                ALUOp = 2'b01; // 比较操作
                imm = {{19{instr[31]}}, instr[31], instr[7], instr[30:25], instr[11:8], 1'b0};  // B-Type 的立即数
            end
            7'b1101111: begin  // J-Type 跳转指令 (jal)
                RegWrite = 1;
                ALUSrc = 1;    // ALU 的输入来自立即数（跳转目标地址）
                MemtoReg = 0;
                MemRead = 0;
                MemWrite = 0;
                Branch = 0;    // 直接跳转
                ALUOp = 2'b00; // 直接跳转
                imm = {{12{instr[31]}}, instr[19:12], instr[20], instr[30:21], 1'b0};  // J-Type 的立即数
            end
            7'b1100111: begin  // I-Type 跳转指令 (jalr)
                RegWrite = 1;
                ALUSrc = 1;    // ALU 的输入来自立即数（跳转目标地址）
                MemtoReg = 0;
                MemRead = 0;
                MemWrite = 0;
                Branch = 0;    // 直接跳转
                ALUOp = 2'b00; // 直接跳转
                imm = {{20{instr[31]}}, instr[31:20]};  // I-Type 的立即数
            end
            default: begin
                // 默认情况下所有控制信号保持为 0
                RegWrite = 0;
                MemRead = 0;
                MemWrite = 0;
                MemtoReg = 0;
                ALUSrc = 0;
                Branch = 0;
                ALUOp = 2'b00;
                imm = 32'b0;
                shamt = 5'b0;
            end
        endcase
    end

endmodule

decoder/tbdecoder.v
`timescale 1ns/100ps

module Decoder_tb;
    // 输入
    reg [31:0] instr;
    // 输出
    wire [4:0] rs1, rs2, rd, shamt;
    wire [2:0] funct3;
    wire [6:0] funct7, opcode;
    wire [31:0] imm;
    wire RegWrite, MemRead, MemWrite, MemtoReg, ALUSrc, Branch;
    wire [1:0] ALUOp;

    // 实例化解码器
    Decoder uut (
        .instr(instr),
        .rs1(rs1),
        .rs2(rs2),
        .rd(rd),
        .funct3(funct3),
        .funct7(funct7),
        .opcode(opcode),
        .imm(imm),
        .shamt(shamt),           // 添加 shamt 信号
        .RegWrite(RegWrite),
        .MemRead(MemRead),
        .MemWrite(MemWrite),
        .MemtoReg(MemtoReg),
        .ALUSrc(ALUSrc),
        .Branch(Branch),
        .ALUOp(ALUOp)
    );

    initial begin
        $dumpfile("decoder_tb.vcd");
        $dumpvars(0, Decoder_tb);

        // R-Type (add x1, x2, x3)
        instr = 32'b0000000_00011_00010_000_00001_0110011; // add x1, x2, x3
        #10;
        $display("R-Type: add, rs1 = %d, rs2 = %d, rd = %d, funct3 = %b, funct7 = %b, RegWrite = %b", rs1, rs2, rd, funct3, funct7, RegWrite);

        // I-Type (addi x1, x2, 1)
        instr = 32'b000000000001_00010_000_00001_0010011; // addi x1, x2, 1
        #10;
        $display("I-Type: addi, rs1 = %d, imm = %d, rd = %d, ALUSrc = %b, RegWrite = %b", rs1, imm, rd, ALUSrc, RegWrite);

        // S-Type (sw x1, 0(x2))
        instr = 32'b0000000_00001_00010_010_00000_0100011; // sw x1, 0(x2)
        #10;
        $display("S-Type: sw, rs1 = %d, rs2 = %d, imm = %d, MemWrite = %b", rs1, rs2, imm, MemWrite);

        // B-Type (beq x1, x2, offset)
        instr = 32'b0000000_00010_00001_000_00010_1100011; // beq x1, x2, offset
        #10;
        $display("B-Type: beq, rs1 = %d, rs2 = %d, imm = %d, Branch = %b", rs1, rs2, imm, Branch);

        // J-Type (jal x1, offset)
        instr = 32'b000000000100_00000_110_00001_1101111; // jal x1, offset
        #10;
        $display("J-Type: jal, rd = %d, imm = %d, RegWrite = %b", rd, imm, RegWrite);

        // I-Type (lw x4, 0(x5))
        instr = 32'b000000000000_00101_010_00100_0000011;  // lw x4, 0(x5)
        #10;
        $display("I-Type: lw, rs1 = %d, imm = %d, rd = %d, MemRead = %b", rs1, imm, rd, MemRead);

        // I-Type 移位指令 (slli x1, x2, 1)
        instr = 32'b0000000_00001_00010_001_00001_0010011;  // slli x1, x2, 1
        #10;
        $display("I-Type: slli, rs1 = %d, shamt = %d, rd = %d, ALUSrc = %b, RegWrite = %b", rs1, shamt, rd, ALUSrc, RegWrite);

        // I-Type 移位指令 (srli x1, x2, 1)
        instr = 32'b0000000_00001_00010_101_00001_0010011;  // srli x1, x2, 1
        #10;
        $display("I-Type: srli, rs1 = %d, shamt = %d, rd = %d, ALUSrc = %b, RegWrite = %b", rs1, shamt, rd, ALUSrc, RegWrite);

        // I-Type 移位指令 (srai x1, x2, 1)
        instr = 32'b0100000_00001_00010_101_00001_0010011;  // srai x1, x2, 1
        #10;
        $display("I-Type: srai, rs1 = %d, shamt = %d, rd = %d, ALUSrc = %b, RegWrite = %b", rs1, shamt, rd, ALUSrc, RegWrite);

        $finish;
    end
endmodule

decoder/decoder_tb.vcd
$date
	Sat Sep 28 21:18:39 2024
$end
$version
	Icarus Verilog
$end
$timescale
	100ps
$end
$scope module Decoder_tb $end
$var wire 5 ! shamt [4:0] $end
$var wire 5 " rs2 [4:0] $end
$var wire 5 # rs1 [4:0] $end
$var wire 5 $ rd [4:0] $end
$var wire 7 % opcode [6:0] $end
$var wire 32 & imm [31:0] $end
$var wire 7 ' funct7 [6:0] $end
$var wire 3 ( funct3 [2:0] $end
$var wire 1 ) RegWrite $end
$var wire 1 * MemtoReg $end
$var wire 1 + MemWrite $end
$var wire 1 , MemRead $end
$var wire 1 - Branch $end
$var wire 1 . ALUSrc $end
$var wire 2 / ALUOp [1:0] $end
$var reg 32 0 instr [31:0] $end
$scope module uut $end
$var wire 32 1 instr [31:0] $end
$var reg 2 2 ALUOp [1:0] $end
$var reg 1 . ALUSrc $end
$var reg 1 - Branch $end
$var reg 1 , MemRead $end
$var reg 1 + MemWrite $end
$var reg 1 * MemtoReg $end
$var reg 1 ) RegWrite $end
$var reg 3 3 funct3 [2:0] $end
$var reg 7 4 funct7 [6:0] $end
$var reg 32 5 imm [31:0] $end
$var reg 7 6 opcode [6:0] $end
$var reg 5 7 rd [4:0] $end
$var reg 5 8 rs1 [4:0] $end
$var reg 5 9 rs2 [4:0] $end
$var reg 5 : shamt [4:0] $end
$upscope $end
$upscope $end
$enddefinitions $end
#0
$dumpvars
b0 :
b11 9
b10 8
b1 7
b110011 6
b0 5
b0 4
b0 3
b10 2
b1100010000000010110011 1
b1100010000000010110011 0
b10 /
0.
0-
0,
0+
0*
1)
b0 (
b0 '
b0 &
b110011 %
b1 $
b10 #
b11 "
b0 !
$end
#100
b1 &
b1 5
1.
b11 /
b11 2
1)
b1 "
b1 9
b10011 %
b10011 6
b100010000000010010011 0
b100010000000010010011 1
#200
1+
b0 /
b0 2
1.
0)
b0 &
b0 5
b10 (
b10 3
b0 $
b0 7
b100011 %
b100011 6
b100010010000000100011 0
b100010010000000100011 1
#300
b10 &
b10 5
b1 /
b1 2
1-
0.
0+
b10 "
b10 9
b1 #
b1 8
b0 (
b0 3
b10 $
b10 7
b1100011 %
b1100011 6
b1000001000000101100011 0
b1000001000000101100011 1
#400
1.
1)
b0 /
b0 2
0-
b110000000000100 &
b110000000000100 5
b100 "
b100 9
b0 #
b0 8
b110 (
b110 3
b1 $
b1 7
b1101111 %
b1101111 6
b10000000110000011101111 0
b10000000110000011101111 1
#500
1,
1*
1.
1)
b0 &
b0 5
b0 "
b0 9
b101 #
b101 8
b10 (
b10 3
b100 $
b100 7
b11 %
b11 6
b101010001000000011 0
b101010001000000011 1
#600
b1 &
b1 5
b11 /
b11 2
1.
0*
0,
1)
b1 "
b1 9
b10 #
b10 8
b1 (
b1 3
b1 $
b1 7
b10011 %
b10011 6
b100010001000010010011 0
b100010001000010010011 1
#700
b11 /
b11 2
1.
1)
b1 &
b1 5
b101 (
b101 3
b100010101000010010011 0
b100010101000010010011 1
#800
b11 /
b11 2
1.
1)
b10000000001 &
b10000000001 5
b100000 '
b100000 4
b1000000000100010101000010010011 0
b1000000000100010101000010010011 1
