instmem.v
`timescale 1ns/100ps

module Instr_Mem (
    input wire [31:0] addr,  // programming counter addr (motion that should do)
    output reg [31:0] instr  // instr output
);

    reg [31:0] memory [0:65535]; //64k instr = 128kbyte
    // initial (wouldn't change if u don't want to do more)
    initial begin
// ********************整數運算*********************
// opcode rs rs2 rd imm	
//(R-type)
        memory[0]  = 32'b0000000_00011_00010_000_00001_0110011; // add x1, x2, x3
        memory[1]  = 32'b0100000_00011_00010_000_00001_0110011; // sub x1, x2, x3
        memory[2]  = 32'b0000000_00011_00010_100_00001_0110011; // xor x1, x2, x3
        memory[3]  = 32'b0000000_00011_00010_110_00001_0110011; // or x1, x2, x3
        memory[4]  = 32'b0000000_00011_00010_111_00001_0110011; // and x1, x2, x3
        memory[5]  = 32'b0000000_00011_00010_001_00001_0110011; // sll x1, x2, x3
        memory[6]  = 32'b0000000_00011_00010_101_00001_0110011; // srl x1, x2, x3
        memory[7]  = 32'b0100000_00011_00010_101_00001_0110011; // sra x1, x2, x3
        memory[8]  = 32'b0000000_00011_00010_010_00001_0110011; // slt x1, x2, x3
        memory[9]  = 32'b0000000_00011_00010_011_00001_0110011; // sltu x1, x2, x3
        
//(I-type)						       								
        memory[10] = 32'b000000000001_00010_000_00001_0010011; // addi x1, x2, 1
        memory[11] = 32'b000000000001_00010_100_00001_0010011; // xori x1, x2, 1
        memory[12] = 32'b000000000001_00010_110_00001_0010011; // ori x1, x2, 1
        memory[13] = 32'b000000000001_00010_111_00001_0010011; // andi x1, x2, 1
        memory[14] = 32'b000000000001_00010_001_00001_0010011; // slli x1, x2, 1 (shamt) 
        memory[15] = 32'b000000000001_00010_101_00001_0010011; // srli x1, x2, 1 (shamt)
        memory[16] = 32'b010000000001_00010_101_00001_0010011; // srai x1, x2, 1 (shamt)
        memory[17] = 32'b000000000001_00010_010_00001_0010011; // slti x1, x2, 1
        memory[18] = 32'b000000000001_00010_011_00001_0010011; // sltiu x1, x2, 1
//(U-type)
	memory[19] = 32'b000000000001_00010_000_00001_0110111; // lui imm rd 1
        memory[20] = 32'b000000000001_00010_100_00001_0010111; // auipe 
// ********************條件跳轉*********************
// (B-type)
        memory[21] = 32'b0000000_00010_00001_000_00010_1100011; // beq x1, x2, offset
        memory[22] = 32'b0000000_00010_00001_001_00010_1100011; // bne x1, x2, offset
        memory[23] = 32'b0000000_00010_00001_100_00010_1100011; // blt x1, x2, offset
        memory[24] = 32'b0000000_00010_00001_101_00010_1100011; // bge x1, x2, offset
        memory[25] = 32'b0000000_00010_00001_110_00010_1100011; // bltu x1, x2, offset
        memory[26] = 32'b0000000_00010_00001_111_00010_1100011; // bgeu x1, x2, offset
// (J-type)
        memory[27] = 32'b000000000100_00000_110_00001_1101111; // jal x1, offset
        memory[28] = 32'b000000000100_00001_000_00010_1100111; // jalr x2, x1, offset

// ********************reading instru*********************
        memory[29] = 32'b000000000000_00101_010_00100_0000011;  // lw x4, 0(x5)
        memory[30] = 32'b000000000000_00101_000_00100_0000011;  // lb x4, 0(x5)
        memory[31] = 32'b000000000000_00101_001_00100_0000011;  // lh x4, 0(x5)
        memory[32] = 32'b000000000000_00101_100_00100_0000011;  // lbu x4, 0(x5)
        memory[33] = 32'b000000000000_00101_101_00100_0000011;  // lhu x4, 0(x5)
        memory[34] = 32'b0000000_00001_00010_010_00000_0100011; // sw x1, 0(x2)
        memory[35] = 32'b0000000_00001_00010_000_00000_0100011; // sb x1, 0(x2)
        memory[36] = 32'b0000000_00001_00010_001_00000_0100011; // sh x1, 0(x2)

//********************pesudo instr*********************
        memory[37] = 32'b000000000000_00000_000_00000_0010011; // nop (addi x0, x0, 0)
        memory[38] = 32'b000000000000_00001_000_00010_0110011; // mv x2, x1 (add x2, x1, x0)
        memory[39] = 32'b000000000000_00000_000_00001_0010011; // li x1, 0 (addi x1, x0, 0)
        memory[40] = 32'b000000000100_00000_110_00001_1101111; // call (jal x1, offset)
        memory[41] = 32'b000000000000_00001_000_00010_1100111; // ret (jalr x0, x1, 0)


    end
// 共41條指令
    // IF
    always @(*) begin
        instr = memory[addr[17:2]]; // addr[17:2]
	// 2^16 = 65535 
	// 每條指令間隔4bytes +4 > 省略01 ＝ 1 / 00 ＝ 0 / 11 ＝ 3 / 10 ＝ 2 的可能
    end
endmodule

instrmem/tbinstmem.v
`timescale 1ns/100ps

module Instr_Mem_tb;
    reg [31:0] addr;

    
    wire [31:0] instr;  

  
    Instr_Mem uut (
        .addr(addr),
        .instr(instr)
    );

  
    integer i;  

    initial begin
        $dumpfile("instr.vcd");
        $dumpvars;

        for (i = 0; i < 42; i = i + 1) begin
            addr = i * 4;  
            #10;           
            $display("Test %0d: Addr = %0d, Instr = %b", i + 1, addr, instr);
        end

        $finish;
    end
endmodule

instrmem/instr.vcd
$date
	Sat Sep 28 16:54:12 2024
$end
$version
	Icarus Verilog
$end
$timescale
	100ps
$end
$scope module Instr_Mem_tb $end
$var wire 32 ! instr [31:0] $end
$var reg 32 " addr [31:0] $end
$var integer 32 # i [31:0] $end
$scope module uut $end
$var wire 32 $ addr [31:0] $end
$var reg 32 % instr [31:0] $end
$upscope $end
$upscope $end
$enddefinitions $end
#0
$dumpvars
b1100010000000010110011 %
b0 $
b0 #
b0 "
b1100010000000010110011 !
$end
#100
b1000000001100010000000010110011 !
b1000000001100010000000010110011 %
b100 "
b100 $
b1 #
#200
b1100010100000010110011 !
b1100010100000010110011 %
b1000 "
b1000 $
b10 #
#300
b1100010110000010110011 !
b1100010110000010110011 %
b1100 "
b1100 $
b11 #
#400
b1100010111000010110011 !
b1100010111000010110011 %
b10000 "
b10000 $
b100 #
#500
b1100010001000010110011 !
b1100010001000010110011 %
b10100 "
b10100 $
b101 #
#600
b1100010101000010110011 !
b1100010101000010110011 %
b11000 "
b11000 $
b110 #
#700
b1000000001100010101000010110011 !
b1000000001100010101000010110011 %
b11100 "
b11100 $
b111 #
#800
b1100010010000010110011 !
b1100010010000010110011 %
b100000 "
b100000 $
b1000 #
#900
b1100010011000010110011 !
b1100010011000010110011 %
b100100 "
b100100 $
b1001 #
#1000
b100010000000010010011 !
b100010000000010010011 %
b101000 "
b101000 $
b1010 #
#1100
b100010100000010010011 !
b100010100000010010011 %
b101100 "
b101100 $
b1011 #
#1200
b100010110000010010011 !
b100010110000010010011 %
b110000 "
b110000 $
b1100 #
#1300
b100010111000010010011 !
b100010111000010010011 %
b110100 "
b110100 $
b1101 #
#1400
b100010001000010010011 !
b100010001000010010011 %
b111000 "
b111000 $
b1110 #
#1500
b100010101000010010011 !
b100010101000010010011 %
b111100 "
b111100 $
b1111 #
#1600
b1000000000100010101000010010011 !
b1000000000100010101000010010011 %
b1000000 "
b1000000 $
b10000 #
#1700
b100010010000010010011 !
b100010010000010010011 %
b1000100 "
b1000100 $
b10001 #
#1800
b100010011000010010011 !
b100010011000010010011 %
b1001000 "
b1001000 $
b10010 #
#1900
b100010000000010110111 !
b100010000000010110111 %
b1001100 "
b1001100 $
b10011 #
#2000
b100010100000010010111 !
b100010100000010010111 %
b1010000 "
b1010000 $
b10100 #
#2100
b1000001000000101100011 !
b1000001000000101100011 %
b1010100 "
b1010100 $
b10101 #
#2200
b1000001001000101100011 !
b1000001001000101100011 %
b1011000 "
b1011000 $
b10110 #
#2300
b1000001100000101100011 !
b1000001100000101100011 %
b1011100 "
b1011100 $
b10111 #
#2400
b1000001101000101100011 !
b1000001101000101100011 %
b1100000 "
b1100000 $
b11000 #
#2500
b1000001110000101100011 !
b1000001110000101100011 %
b1100100 "
b1100100 $
b11001 #
#2600
b1000001111000101100011 !
b1000001111000101100011 %
b1101000 "
b1101000 $
b11010 #
#2700
b10000000110000011101111 !
b10000000110000011101111 %
b1101100 "
b1101100 $
b11011 #
#2800
b10000001000000101100111 !
b10000001000000101100111 %
b1110000 "
b1110000 $
b11100 #
#2900
b101010001000000011 !
b101010001000000011 %
b1110100 "
b1110100 $
b11101 #
#3000
b101000001000000011 !
b101000001000000011 %
b1111000 "
b1111000 $
b11110 #
#3100
b101001001000000011 !
b101001001000000011 %
b1111100 "
b1111100 $
b11111 #
#3200
b101100001000000011 !
b101100001000000011 %
b10000000 "
b10000000 $
b100000 #
#3300
b101101001000000011 !
b101101001000000011 %
b10000100 "
b10000100 $
b100001 #
#3400
b100010010000000100011 !
b100010010000000100011 %
b10001000 "
b10001000 $
b100010 #
#3500
b100010000000000100011 !
b100010000000000100011 %
b10001100 "
b10001100 $
b100011 #
#3600
b100010001000000100011 !
b100010001000000100011 %
b10010000 "
b10010000 $
b100100 #
#3700
b10011 !
b10011 %
b10010100 "
b10010100 $
b100101 #
#3800
b1000000100110011 !
b1000000100110011 %
b10011000 "
b10011000 $
b100110 #
#3900
b10010011 !
b10010011 %
b10011100 "
b10011100 $
b100111 #
#4000
b10000000110000011101111 !
b10000000110000011101111 %
b10100000 "
b10100000 $
b101000 #
#4100
b1000000101100111 !
b1000000101100111 %
b10100100 "
b10100100 $
b101001 #
#4200
b101010 #
