alu/alu.v
module ALU (
    input [31:0] A,           
    input [31:0] B,           
    input [1:0] ALUOp,        
    input [2:0] funct3,       
    input [4:0] shamt,        
    input [6:0] funct7,      
    output reg [31:0] Result, 
    output Zero,
    output reg Less               
);

    assign Zero = (Result == 32'b0);

    always @(*) begin
        Less = ($signed(A) < $signed(B)) ? 1'b1 : 1'b0;
        
        case (ALUOp)
            2'b00: begin 
                if (funct7 == 7'b0100000) 
                    Result = A - B;  // 减法
                else                       
                    Result = A + B;  // 加法
            end
            2'b01: begin  
                case (funct3)
                    3'b000: Result = A & B;  // AND
                    3'b001: Result = A | B;  // OR
                    3'b010: Result = A ^ B;  // XOR
                    default: Result = 32'b0;
                endcase
            end
            2'b10: begin  // 移位操作
                case (funct3)
                    3'b000: Result = A << shamt;  // 左移
                    3'b101: begin
                        if (funct7 == 7'b0100000)
                            Result = $signed(A) >>> shamt;  
                        else
                            Result = A >> shamt;  
                    end
                    default: Result = 32'b0;
                endcase
            end
            2'b11: begin  
                if (funct3 == 3'b010)
                    Result = ($signed(A) < $signed(B)) ? 32'b1 : 32'b0;  // slt 
                else if (funct3 == 3'b011)
                    Result = (A < B) ? 32'b1 : 32'b0;  // sltu
                else
                    Result = 32'b0;
            end
            default: Result = 32'b0;
        endcase
    end

endmodule

alu/tb.v
`timescale 1ns/100ps

module ALU_tb;

    reg [31:0] A, B;
    reg [1:0] ALUOp;
    reg [2:0] funct3;
    reg [4:0] shamt;
    reg [6:0] funct7;
    wire [31:0] Result;
    wire Zero;
    wire Less;

    // ALU模組實例化
    ALU uut (
        .A(A),
        .B(B),
        .ALUOp(ALUOp),
        .funct3(funct3),
        .shamt(shamt),
        .funct7(funct7),
        .Result(Result),
        .Zero(Zero),
        .Less(Less)
    );

    // 初始設置
    initial begin
        $dumpfile("ALU_tb.vcd");
        $dumpvars(0, ALU_tb);

        // 測試加法 (ALUOp = 00, funct7 = 0000000)
        A = 32'h0000000A; B = 32'h00000014; ALUOp = 2'b00; funct7 = 7'b0000000; #10;
        $display("Add: A = %h, B = %h, Result = %h, Zero = %b, Less = %b", A, B, Result, Zero, Less);

        // 測試減法 (ALUOp = 00, funct7 = 0100000)
        A = 32'h00000014; B = 32'h0000000A; ALUOp = 2'b00; funct7 = 7'b0100000; #10;
        $display("Sub: A = %h, B = %h, Result = %h, Zero = %b, Less = %b", A, B, Result, Zero, Less);

        // 測試 AND (ALUOp = 01, funct3 = 000)
        A = 32'h0F0F0F0F; B = 32'h00FF00FF; ALUOp = 2'b01; funct3 = 3'b000; #10;
        $display("AND: A = %h, B = %h, Result = %h, Zero = %b, Less = %b", A, B, Result, Zero, Less);

        // 測試 OR (ALUOp = 01, funct3 = 001)
        A = 32'h0F0F0F0F; B = 32'h00FF00FF; ALUOp = 2'b01; funct3 = 3'b001; #10;
        $display("OR: A = %h, B = %h, Result = %h, Zero = %b, Less = %b", A, B, Result, Zero, Less);

        // 測試 XOR (ALUOp = 01, funct3 = 010)
        A = 32'h0F0F0F0F; B = 32'h00FF00FF; ALUOp = 2'b01; funct3 = 3'b010; #10;
        $display("XOR: A = %h, B = %h, Result = %h, Zero = %b, Less = %b", A, B, Result, Zero, Less);

        // 測試 SLL (左移操作) (ALUOp = 10, funct3 = 000)
        A = 32'h00000001; shamt = 5; ALUOp = 2'b10; funct3 = 3'b000; #10;
        $display("SLL: A = %h, shamt = %d, Result = %h, Zero = %b, Less = %b", A, shamt, Result, Zero, Less);

        // 測試 SRL (邏輯右移) (ALUOp = 10, funct3 = 101, funct7 = 0000000)
        A = 32'h00000020; shamt = 2; ALUOp = 2'b10; funct3 = 3'b101; funct7 = 7'b0000000; #10;
        $display("SRL: A = %h, shamt = %d, Result = %h, Zero = %b, Less = %b", A, shamt, Result, Zero, Less);

        // 測試 SRA (算術右移) (ALUOp = 10, funct3 = 101, funct7 = 0100000)
        A = 32'hFFFFFFE0; shamt = 2; ALUOp = 2'b10; funct3 = 3'b101; funct7 = 7'b0100000; #10;
        $display("SRA: A = %h, shamt = %d, Result = %h, Zero = %b, Less = %b", A, shamt, Result, Zero, Less);

        // 測試 SLT (小於比較，有符號) (ALUOp = 11, funct3 = 010)
        A = 32'h00000001; B = 32'h00000002; ALUOp = 2'b11; funct3 = 3'b010; #10;
        $display("SLT: A = %h, B = %h, Result = %h, Zero = %b, Less = %b", A, B, Result, Zero, Less);

        // 測試 SLTU (小於比較，無符號) (ALUOp = 11, funct3 = 011)
        A = 32'hFFFFFFFE; B = 32'h00000001; ALUOp = 2'b11; funct3 = 3'b011; #10;
        $display("SLTU: A = %h, B = %h, Result = %h, Zero = %b, Less = %b", A, B, Result, Zero, Less);

        // 測試零輸出
        A = 32'h00000000; B = 32'h00000000; ALUOp = 2'b00; funct7 = 7'b0000000; #10;
        $display("Zero Test: A = %h, B = %h, Result = %h, Zero = %b, Less = %b", A, B, Result, Zero, Less);

        // 結束測試
        $finish;
    end
endmodule

alu/ALU_tb.vcd
$date
	Sat Oct  5 21:03:16 2024
$end
$version
	Icarus Verilog
$end
$timescale
	100ps
$end
$scope module ALU_tb $end
$var wire 1 ! Zero $end
$var wire 32 " Result [31:0] $end
$var wire 1 # Less $end
$var reg 32 $ A [31:0] $end
$var reg 2 % ALUOp [1:0] $end
$var reg 32 & B [31:0] $end
$var reg 3 ' funct3 [2:0] $end
$var reg 7 ( funct7 [6:0] $end
$var reg 5 ) shamt [4:0] $end
$scope module uut $end
$var wire 32 * A [31:0] $end
$var wire 2 + ALUOp [1:0] $end
$var wire 32 , B [31:0] $end
$var wire 3 - funct3 [2:0] $end
$var wire 7 . funct7 [6:0] $end
$var wire 5 / shamt [4:0] $end
$var wire 1 ! Zero $end
$var reg 1 # Less $end
$var reg 32 0 Result [31:0] $end
$upscope $end
$upscope $end
$enddefinitions $end
#0
$dumpvars
b11110 0
bx /
b0 .
bx -
b10100 ,
b0 +
b1010 *
bx )
b0 (
bx '
b10100 &
b0 %
b1010 $
1#
b11110 "
0!
$end
#100
b1010 "
b1010 0
0#
b100000 (
b100000 .
b1010 &
b1010 ,
b10100 $
b10100 *
#200
b11110000000000001111 "
b11110000000000001111 0
b0 '
b0 -
b1 %
b1 +
b111111110000000011111111 &
b111111110000000011111111 ,
b1111000011110000111100001111 $
b1111000011110000111100001111 *
#300
b1111111111110000111111111111 "
b1111111111110000111111111111 0
b1 '
b1 -
#400
b1111111100000000111111110000 "
b1111111100000000111111110000 0
b10 '
b10 -
#500
b100000 "
b100000 0
1#
b0 '
b0 -
b10 %
b10 +
b101 )
b101 /
b1 $
b1 *
#600
b1000 "
b1000 0
b0 (
b0 .
b101 '
b101 -
b10 )
b10 /
b100000 $
b100000 *
#700
b11111111111111111111111111111000 "
b11111111111111111111111111111000 0
b100000 (
b100000 .
b11111111111111111111111111100000 $
b11111111111111111111111111100000 *
#800
b1 "
b1 0
b10 '
b10 -
b11 %
b11 +
b10 &
b10 ,
b1 $
b1 *
#900
1!
b0 "
b0 0
b11 '
b11 -
b1 &
b1 ,
b11111111111111111111111111111110 $
b11111111111111111111111111111110 *
#1000
0#
b0 (
b0 .
b0 %
b0 +
b0 &
b0 ,
b0 $
b0 *
