reg+pc+inst+dec/regst.v
`timescale 1ns/100ps

module register_file (
    input wire [4:0] Ra,       // rs1
    input wire [4:0] Rb,       // rs2
    input wire [4:0] Rw,       // rd
    input wire [31:0] busW,    // data write
    input wire RegWr,          // enable
    input wire WrClk,          // clk
    output wire [31:0] busA,   // data read 1
    output wire [31:0] busB,   // data read 2
    output wire [31:0] reg1,   // observe register x1
    output wire [31:0] reg2    // observe register x2
);

    // 32條32位元的寄存器
    reg [31:0] registers [31:0];

    // 讀取寄存器 x0~x31
    assign busA = (Ra == 5'b0) ? 32'b0 : registers[Ra];  // x0 永遠為 0
    assign busB = (Rb == 5'b0) ? 32'b0 : registers[Rb];  // x0 永遠為 0

    // x1 和 x2 的額外輸出端口，用於觀察其值
    assign reg1 = registers[1];
    assign reg2 = registers[2];

    // 在時鐘的下降沿進行寫入操作
    always @(negedge WrClk) begin
        if (RegWr && (Rw != 5'b0)) begin  // x0 無法寫入
            registers[Rw] <= busW;
        end
    end

    // 初始化寄存器為 0
    integer i;
    initial begin
        for (i = 0; i < 32; i = i + 1) begin
            registers[i] = 32'b0;
        end
    end
endmodule

reg+pc+inst+dec/decoder.v
`timescale 1ns/100ps

module Decoder (
    input [31:0] instr,           
    output reg [4:0] rs1,         
    output reg [4:0] rs2,         
    output reg [4:0] rd,          
    output reg [2:0] funct3,      
    output reg [6:0] funct7,      
    output reg [6:0] opcode,      
    output reg [31:0] imm,        
    output reg [4:0] shamt,       
    output reg RegWrite,          
    output reg MemRead,           
    output reg MemWrite,          
    output reg MemToReg,          
    output reg ALUSrc,            
    output reg Branch,            
    output reg Jump,              
    output reg [1:0] ALUOp        
);

    always @(*) begin
        // Extract fields from the instruction
        opcode = instr[6:0];
        rd = instr[11:7];
        funct3 = instr[14:12];
        rs1 = instr[19:15];
        rs2 = instr[24:20];
        funct7 = instr[31:25];

        // Default values
        shamt = instr[24:20];  
        imm = 32'b0;
        RegWrite = 0;
        MemRead = 0;
        MemWrite = 0;
        MemToReg = 0;
        ALUSrc = 0;
        Branch = 0;
        Jump = 0;
        ALUOp = 2'b00;

        case (opcode)
            7'b0110011: begin // R-Type (e.g., add, sub, and, or)
                RegWrite = 1;
                ALUSrc = 0;
                MemToReg = 0;
                MemRead = 0;
                MemWrite = 0;
                Branch = 0;
                ALUOp = 2'b10;
            end
            7'b0010011: begin // I-Type for ALU immediate (e.g., addi, slli)
                RegWrite = 1;
                ALUSrc = 1;
                MemToReg = 0;
                MemRead = 0;
                MemWrite = 0;
                Branch = 0;
                ALUOp = 2'b11;
                imm = {{20{instr[31]}}, instr[31:20]};
                if (funct3 == 3'b001 || funct3 == 3'b101) begin // Shift instructions with immediate
                    shamt = instr[24:20];
                end
            end
            7'b0000011: begin // I-Type Load (e.g., lw, lb)
                RegWrite = 1;
                ALUSrc = 1;
                MemToReg = 1;
                MemRead = 1;
                MemWrite = 0;
                Branch = 0;
                ALUOp = 2'b00;
                imm = {{20{instr[31]}}, instr[31:20]};
            end
            7'b0100011: begin // S-Type Store (e.g., sw, sb)
                RegWrite = 0;
                ALUSrc = 1;
                MemToReg = 0;
                MemRead = 0;
                MemWrite = 1;
                Branch = 0;
                ALUOp = 2'b00;
                imm = {{20{instr[31]}}, instr[31:25], instr[11:7]};
            end
            7'b1100011: begin // B-Type Branch (e.g., beq, bne)
                RegWrite = 0;
                ALUSrc = 0;
                MemToReg = 0;
                MemRead = 0;
                MemWrite = 0;
                Branch = 1;
                ALUOp = 2'b01;
                imm = {{20{instr[31]}}, instr[7], instr[30:25], instr[11:8], 1'b0};
            end
            7'b1101111: begin // J-Type Jump (e.g., jal)
                RegWrite = 1;
                ALUSrc = 1;
                MemToReg = 0;
                MemRead = 0;
                MemWrite = 0;
                Branch = 0;
                Jump = 1;
                ALUOp = 2'b00;
                imm = {{12{instr[31]}}, instr[19:12], instr[20], instr[30:21], 1'b0};
            end
            7'b1100111: begin // I-Type Jump Register (e.g., jalr)
                RegWrite = 1;
                ALUSrc = 1;
                MemToReg = 0;
                MemRead = 0;
                MemWrite = 0;
                Branch = 0;
                Jump = 1;
                ALUOp = 2'b00;
                imm = {{20{instr[31]}}, instr[31:20]};
            end
            default: begin
                RegWrite = 0;
                MemRead = 0;
                MemWrite = 0;
                MemToReg = 0;
                ALUSrc = 0;
                Branch = 0;
                Jump = 0;
                ALUOp = 2'b00;
                imm = 32'b0;
                shamt = 5'b0;
            end
        endcase
    end

endmodule

instmem.v
`timescale 1ns/100ps

module Instr_Mem (
    input wire [31:0] addr,  // programming counter addr (motion that should do)
    output reg [31:0] instr  // instr output
);

    reg [31:0] memory [0:65535]; //64k instr = 128kbyte
    // initial (wouldn't change if u don't want to do more)
    initial begin
// ********************整數運算*********************
// opcode rs rs2 rd imm	
//(R-type)
        memory[0]  = 32'b0000000_00011_00010_000_00001_0110011; // add x1, x2, x3
        memory[1]  = 32'b0100000_00011_00010_000_00001_0110011; // sub x1, x2, x3
        memory[2]  = 32'b0000000_00011_00010_100_00001_0110011; // xor x1, x2, x3
        memory[3]  = 32'b0000000_00011_00010_110_00001_0110011; // or x1, x2, x3
        memory[4]  = 32'b0000000_00011_00010_111_00001_0110011; // and x1, x2, x3
        memory[5]  = 32'b0000000_00011_00010_001_00001_0110011; // sll x1, x2, x3
        memory[6]  = 32'b0000000_00011_00010_101_00001_0110011; // srl x1, x2, x3
        memory[7]  = 32'b0100000_00011_00010_101_00001_0110011; // sra x1, x2, x3
        memory[8]  = 32'b0000000_00011_00010_010_00001_0110011; // slt x1, x2, x3
        memory[9]  = 32'b0000000_00011_00010_011_00001_0110011; // sltu x1, x2, x3
        
//(I-type)						       								
        memory[10] = 32'b000000000001_00010_000_00001_0010011; // addi x1, x2, 1
        memory[11] = 32'b000000000001_00010_100_00001_0010011; // xori x1, x2, 1
        memory[12] = 32'b000000000001_00010_110_00001_0010011; // ori x1, x2, 1
        memory[13] = 32'b000000000001_00010_111_00001_0010011; // andi x1, x2, 1
        memory[14] = 32'b000000000001_00010_001_00001_0010011; // slli x1, x2, 1 (shamt) 
        memory[15] = 32'b000000000001_00010_101_00001_0010011; // srli x1, x2, 1 (shamt)
        memory[16] = 32'b010000000001_00010_101_00001_0010011; // srai x1, x2, 1 (shamt)
        memory[17] = 32'b000000000001_00010_010_00001_0010011; // slti x1, x2, 1
        memory[18] = 32'b000000000001_00010_011_00001_0010011; // sltiu x1, x2, 1
//(U-type)
	memory[19] = 32'b000000000001_00010_000_00001_0110111; // lui imm rd 1
        memory[20] = 32'b000000000001_00010_100_00001_0010111; // auipe 
// ********************條件跳轉*********************
// (B-type)
        memory[21] = 32'b0000000_00010_00001_000_00010_1100011; // beq x1, x2, offset
        memory[22] = 32'b0000000_00010_00001_001_00010_1100011; // bne x1, x2, offset
        memory[23] = 32'b0000000_00010_00001_100_00010_1100011; // blt x1, x2, offset
        memory[24] = 32'b0000000_00010_00001_101_00010_1100011; // bge x1, x2, offset
        memory[25] = 32'b0000000_00010_00001_110_00010_1100011; // bltu x1, x2, offset
        memory[26] = 32'b0000000_00010_00001_111_00010_1100011; // bgeu x1, x2, offset
// (J-type)
        memory[27] = 32'b000000000100_00000_110_00001_1101111; // jal x1, offset
        memory[28] = 32'b000000000100_00001_000_00010_1100111; // jalr x2, x1, offset

// ********************reading instru*********************
        memory[29] = 32'b000000000000_00101_010_00100_0000011;  // lw x4, 0(x5)
        memory[30] = 32'b000000000000_00101_000_00100_0000011;  // lb x4, 0(x5)
        memory[31] = 32'b000000000000_00101_001_00100_0000011;  // lh x4, 0(x5)
        memory[32] = 32'b000000000000_00101_100_00100_0000011;  // lbu x4, 0(x5)
        memory[33] = 32'b000000000000_00101_101_00100_0000011;  // lhu x4, 0(x5)
        memory[34] = 32'b0000000_00001_00010_010_00000_0100011; // sw x1, 0(x2)
        memory[35] = 32'b0000000_00001_00010_000_00000_0100011; // sb x1, 0(x2)
        memory[36] = 32'b0000000_00001_00010_001_00000_0100011; // sh x1, 0(x2)

//********************pesudo instr*********************
        memory[37] = 32'b000000000000_00000_000_00000_0010011; // nop (addi x0, x0, 0)
        memory[38] = 32'b000000000000_00001_000_00010_0110011; // mv x2, x1 (add x2, x1, x0)
        memory[39] = 32'b000000000000_00000_000_00001_0010011; // li x1, 0 (addi x1, x0, 0)
        memory[40] = 32'b000000000100_00000_110_00001_1101111; // call (jal x1, offset)
        memory[41] = 32'b000000000000_00001_000_00010_1100111; // ret (jalr x0, x1, 0)


    end
// 共41條指令
    // IF
    always @(*) begin
        instr = memory[addr[17:2]]; // addr[17:2]
	// 2^16 = 65535 
	// 每條指令間隔4bytes +4 > 省略01 ＝ 1 / 00 ＝ 0 / 11 ＝ 3 / 10 ＝ 2 的可能
    end
endmodule

withoutmem/pc.v
`timescale 1ns/100ps

module PC (
    input wire clk,             
    input wire reset,           
    input wire [31:0] next_pc,  
    output reg [31:0] pc         
);

  
    initial begin
        pc = 32'b0;
    end


    always @(posedge clk or posedge reset) begin
        if (reset) begin
            pc <= 32'b0;          
        end else begin
            pc <= next_pc;        
        end
    end

endmodule

reg+pc+inst+dec/cpupart.v
`timescale 1ns/100ps

module CPU (
    input wire clk,
    input wire reset
);

    wire [31:0] pc, next_pc, instr, busA, busB, imm;
    wire [4:0] rs1, rs2, rd, shamt;
    wire [2:0] funct3;
    wire [6:0] funct7, opcode;
    wire RegWrite, MemRead, MemWrite, MemToReg, ALUSrc, Branch, Jump;
    wire [1:0] ALUOp;

    // Program Counter (PC)
    PC pc_reg (
        .clk(clk),
        .reset(reset),
        .next_pc(next_pc),
        .pc(pc)
    );

    // Instruction Memory
    Instr_Mem instr_mem (
        .addr(pc),
        .instr(instr)
    );

    // Decoder
    Decoder decoder (
        .instr(instr),
        .rs1(rs1),
        .rs2(rs2),
        .rd(rd),
        .funct3(funct3),
        .funct7(funct7),
        .opcode(opcode),
        .imm(imm),
        .shamt(shamt),
        .RegWrite(RegWrite),
        .MemRead(MemRead),
        .MemWrite(MemWrite),
        .MemToReg(MemToReg),
        .ALUSrc(ALUSrc),
        .Branch(Branch),
        .Jump(Jump),
        .ALUOp(ALUOp)
    );

    // Register File
    register_file reg_file (
        .Ra(rs1),
        .Rb(rs2),
        .Rw(rd),
        .busW(32'd0),      
        .RegWr(RegWrite),  
        .WrClk(clk),
        .busA(busA),
        .busB(busB)
    );

    // PC Update Logic
    assign next_pc = pc + 4; // PC increment by 4 for next instruction

endmodule

reg+pc+inst+dec/tb.v
`timescale 1ns/100ps

module CPU_tb;
    reg clk;
    reg reset;
    wire [31:0] pc, instr, busA, busB, imm;
    wire [4:0] rs1, rs2, rd, shamt;
    wire [2:0] funct3;
    wire [6:0] funct7, opcode;
    wire RegWrite, MemRead, MemWrite, MemToReg, ALUSrc, Branch, Jump;
    wire [1:0] ALUOp;

    // Instantiate CPU
    CPU cpu (
        .clk(clk),
        .reset(reset)
    );

    // Assign signals for monitoring
    assign pc = cpu.pc_reg.pc;
    assign instr = cpu.instr_mem.instr;
    assign rs1 = cpu.decoder.rs1;
    assign rs2 = cpu.decoder.rs2;
    assign rd = cpu.decoder.rd;
    assign funct3 = cpu.decoder.funct3;
    assign funct7 = cpu.decoder.funct7;
    assign opcode = cpu.decoder.opcode;
    assign imm = cpu.decoder.imm;
    assign shamt = cpu.decoder.shamt;
    assign RegWrite = cpu.decoder.RegWrite;
    assign MemRead = cpu.decoder.MemRead;
    assign MemWrite = cpu.decoder.MemWrite;
    assign MemToReg = cpu.decoder.MemToReg;
    assign ALUSrc = cpu.decoder.ALUSrc;
    assign Branch = cpu.decoder.Branch;
    assign Jump = cpu.decoder.Jump;
    assign ALUOp = cpu.decoder.ALUOp;
    assign busA = cpu.reg_file.busA;
    assign busB = cpu.reg_file.busB;

    // Clock Generation
    always #5 clk = ~clk;

    initial begin
        // Initialize signals
        clk = 0;
        reset = 1;
        #10;
        
        reset = 0;  // release reset

        // Test with multiple clock cycles
        #1000;  // Adjust time as needed to cover all instructions
        $finish;
    end

    // Monitor output at each clock cycle
    initial begin
        $monitor("Time: %0t | PC: %b | Instr: %b | rs1: %h | rs2: %h | rd: %h | funct3: %h | funct7: %h | opcode: %h | imm: %h | shamt: %h | RegWrite: %b | MemRead: %b | MemWrite: %b | ALUSrc: %b | Branch: %b | Jump: %b | ALUOp: %b | busA: %h | busB: %h", 
                 $time, pc, instr, rs1, rs2, rd, funct3, funct7, opcode, imm, shamt, RegWrite, MemRead, MemWrite, ALUSrc, Branch, Jump, ALUOp, busA, busB);
    end

    initial begin
        $dumpfile("cpu_tb.vcd");
        $dumpvars;
    end
endmodule

reg+pc+inst+dec/cpu_tb.vcd
$date
	Sat Oct  5 20:44:13 2024
$end
$version
	Icarus Verilog
$end
$timescale
	100ps
$end
$scope module CPU_tb $end
$var wire 2 ! ALUOp [1:0] $end
$var wire 1 " ALUSrc $end
$var wire 1 # Branch $end
$var wire 1 $ Jump $end
$var wire 1 % MemRead $end
$var wire 1 & MemToReg $end
$var wire 1 ' MemWrite $end
$var wire 1 ( RegWrite $end
$var wire 32 ) busA [31:0] $end
$var wire 32 * busB [31:0] $end
$var wire 3 + funct3 [2:0] $end
$var wire 7 , funct7 [6:0] $end
$var wire 32 - imm [31:0] $end
$var wire 32 . instr [31:0] $end
$var wire 7 / opcode [6:0] $end
$var wire 32 0 pc [31:0] $end
$var wire 5 1 rd [4:0] $end
$var wire 5 2 rs1 [4:0] $end
$var wire 5 3 rs2 [4:0] $end
$var wire 5 4 shamt [4:0] $end
$var reg 1 5 clk $end
$var reg 1 6 reset $end
$scope module cpu $end
$var wire 1 5 clk $end
$var wire 1 6 reset $end
$var wire 5 7 shamt [4:0] $end
$var wire 5 8 rs2 [4:0] $end
$var wire 5 9 rs1 [4:0] $end
$var wire 5 : rd [4:0] $end
$var wire 32 ; pc [31:0] $end
$var wire 7 < opcode [6:0] $end
$var wire 32 = next_pc [31:0] $end
$var wire 32 > instr [31:0] $end
$var wire 32 ? imm [31:0] $end
$var wire 7 @ funct7 [6:0] $end
$var wire 3 A funct3 [2:0] $end
$var wire 32 B busB [31:0] $end
$var wire 32 C busA [31:0] $end
$var wire 1 D RegWrite $end
$var wire 1 E MemWrite $end
$var wire 1 F MemToReg $end
$var wire 1 G MemRead $end
$var wire 1 H Jump $end
$var wire 1 I Branch $end
$var wire 1 J ALUSrc $end
$var wire 2 K ALUOp [1:0] $end
$scope module decoder $end
$var wire 32 L instr [31:0] $end
$var reg 2 M ALUOp [1:0] $end
$var reg 1 J ALUSrc $end
$var reg 1 I Branch $end
$var reg 1 H Jump $end
$var reg 1 G MemRead $end
$var reg 1 F MemToReg $end
$var reg 1 E MemWrite $end
$var reg 1 D RegWrite $end
$var reg 3 N funct3 [2:0] $end
$var reg 7 O funct7 [6:0] $end
$var reg 32 P imm [31:0] $end
$var reg 7 Q opcode [6:0] $end
$var reg 5 R rd [4:0] $end
$var reg 5 S rs1 [4:0] $end
$var reg 5 T rs2 [4:0] $end
$var reg 5 U shamt [4:0] $end
$upscope $end
$scope module instr_mem $end
$var wire 32 V addr [31:0] $end
$var reg 32 W instr [31:0] $end
$upscope $end
$scope module pc_reg $end
$var wire 1 5 clk $end
$var wire 32 X next_pc [31:0] $end
$var wire 1 6 reset $end
$var reg 32 Y pc [31:0] $end
$upscope $end
$scope module reg_file $end
$var wire 5 Z Ra [4:0] $end
$var wire 5 [ Rb [4:0] $end
$var wire 1 D RegWr $end
$var wire 5 \ Rw [4:0] $end
$var wire 1 5 WrClk $end
$var wire 32 ] busW [31:0] $end
$var wire 32 ^ reg1 [31:0] $end
$var wire 32 _ reg2 [31:0] $end
$var wire 32 ` busB [31:0] $end
$var wire 32 a busA [31:0] $end
$var integer 32 b i [31:0] $end
$upscope $end
$upscope $end
$upscope $end
$enddefinitions $end
#0
$dumpvars
b100000 b
b0 a
b0 `
b0 _
b0 ^
b0 ]
b1 \
b11 [
b10 Z
b0 Y
b100 X
b1100010000000010110011 W
b0 V
b11 U
b11 T
b10 S
b1 R
b110011 Q
b0 P
b0 O
b0 N
b10 M
b1100010000000010110011 L
b10 K
0J
0I
0H
0G
0F
0E
1D
b0 C
b0 B
b0 A
b0 @
b0 ?
b1100010000000010110011 >
b100 =
b110011 <
b0 ;
b1 :
b10 9
b11 8
b11 7
16
05
b11 4
b11 3
b10 2
b1 1
b0 0
b110011 /
b1100010000000010110011 .
b0 -
b0 ,
b0 +
b0 *
b0 )
1(
0'
0&
0%
0$
0#
0"
b10 !
$end
#50
15
#100
05
06
#150
b10 !
b10 K
b10 M
1(
1D
b100000 ,
b100000 @
b100000 O
b1000000001100010000000010110011 .
b1000000001100010000000010110011 >
b1000000001100010000000010110011 L
b1000000001100010000000010110011 W
b1000 =
b1000 X
b100 0
b100 ;
b100 V
b100 Y
15
#200
05
#250
b10 !
b10 K
b10 M
1(
1D
b0 ,
b0 @
b0 O
b100 +
b100 A
b100 N
b1100010100000010110011 .
b1100010100000010110011 >
b1100010100000010110011 L
b1100010100000010110011 W
b1100 =
b1100 X
b1000 0
b1000 ;
b1000 V
b1000 Y
15
#300
05
#350
b10 !
b10 K
b10 M
1(
1D
b110 +
b110 A
b110 N
b1100010110000010110011 .
b1100010110000010110011 >
b1100010110000010110011 L
b1100010110000010110011 W
b10000 =
b10000 X
b1100 0
b1100 ;
b1100 V
b1100 Y
15
#400
05
#450
b10 !
b10 K
b10 M
1(
1D
b111 +
b111 A
b111 N
b1100010111000010110011 .
b1100010111000010110011 >
b1100010111000010110011 L
b1100010111000010110011 W
b10100 =
b10100 X
b10000 0
b10000 ;
b10000 V
b10000 Y
15
#500
05
#550
b10 !
b10 K
b10 M
1(
1D
b1 +
b1 A
b1 N
b1100010001000010110011 .
b1100010001000010110011 >
b1100010001000010110011 L
b1100010001000010110011 W
b11000 =
b11000 X
b10100 0
b10100 ;
b10100 V
b10100 Y
15
#600
05
#650
b10 !
b10 K
b10 M
1(
1D
b101 +
b101 A
b101 N
b1100010101000010110011 .
b1100010101000010110011 >
b1100010101000010110011 L
b1100010101000010110011 W
b11100 =
b11100 X
b11000 0
b11000 ;
b11000 V
b11000 Y
15
#700
05
#750
b10 !
b10 K
b10 M
1(
1D
b100000 ,
b100000 @
b100000 O
b1000000001100010101000010110011 .
b1000000001100010101000010110011 >
b1000000001100010101000010110011 L
b1000000001100010101000010110011 W
b100000 =
b100000 X
b11100 0
b11100 ;
b11100 V
b11100 Y
15
#800
05
#850
b10 !
b10 K
b10 M
1(
1D
b0 ,
b0 @
b0 O
b10 +
b10 A
b10 N
b1100010010000010110011 .
b1100010010000010110011 >
b1100010010000010110011 L
b1100010010000010110011 W
b100100 =
b100100 X
b100000 0
b100000 ;
b100000 V
b100000 Y
15
#900
05
#950
b10 !
b10 K
b10 M
1(
1D
b11 +
b11 A
b11 N
b1100010011000010110011 .
b1100010011000010110011 >
b1100010011000010110011 L
b1100010011000010110011 W
b101000 =
b101000 X
b100100 0
b100100 ;
b100100 V
b100100 Y
15
#1000
05
#1050
b1 -
b1 ?
b1 P
1"
1J
b11 !
b11 K
b11 M
1(
1D
b1 4
b1 7
b1 U
b1 3
b1 8
b1 T
b1 [
b0 +
b0 A
b0 N
b10011 /
b10011 <
b10011 Q
b100010000000010010011 .
b100010000000010010011 >
b100010000000010010011 L
b100010000000010010011 W
b101100 =
b101100 X
b101000 0
b101000 ;
b101000 V
b101000 Y
15
#1100
05
#1150
b11 !
b11 K
b11 M
1"
1J
1(
1D
b1 -
b1 ?
b1 P
b100 +
b100 A
b100 N
b100010100000010010011 .
b100010100000010010011 >
b100010100000010010011 L
b100010100000010010011 W
b110000 =
b110000 X
b101100 0
b101100 ;
b101100 V
b101100 Y
15
#1200
05
#1250
b11 !
b11 K
b11 M
1"
1J
1(
1D
b1 -
b1 ?
b1 P
b110 +
b110 A
b110 N
b100010110000010010011 .
b100010110000010010011 >
b100010110000010010011 L
b100010110000010010011 W
b110100 =
b110100 X
b110000 0
b110000 ;
b110000 V
b110000 Y
15
#1300
05
#1350
b11 !
b11 K
b11 M
1"
1J
1(
1D
b1 -
b1 ?
b1 P
b111 +
b111 A
b111 N
b100010111000010010011 .
b100010111000010010011 >
b100010111000010010011 L
b100010111000010010011 W
b111000 =
b111000 X
b110100 0
b110100 ;
b110100 V
b110100 Y
15
#1400
05
#1450
b11 !
b11 K
b11 M
1"
1J
1(
1D
b1 -
b1 ?
b1 P
b1 +
b1 A
b1 N
b100010001000010010011 .
b100010001000010010011 >
b100010001000010010011 L
b100010001000010010011 W
b111100 =
b111100 X
b111000 0
b111000 ;
b111000 V
b111000 Y
15
#1500
05
#1550
b11 !
b11 K
b11 M
1"
1J
1(
1D
b1 -
b1 ?
b1 P
b101 +
b101 A
b101 N
b100010101000010010011 .
b100010101000010010011 >
b100010101000010010011 L
b100010101000010010011 W
b1000000 =
b1000000 X
b111100 0
b111100 ;
b111100 V
b111100 Y
15
#1600
05
#1650
b11 !
b11 K
b11 M
1"
1J
1(
1D
b10000000001 -
b10000000001 ?
b10000000001 P
b100000 ,
b100000 @
b100000 O
b1000000000100010101000010010011 .
b1000000000100010101000010010011 >
b1000000000100010101000010010011 L
b1000000000100010101000010010011 W
b1000100 =
b1000100 X
b1000000 0
b1000000 ;
b1000000 V
b1000000 Y
15
#1700
05
#1750
b11 !
b11 K
b11 M
1"
1J
1(
1D
b1 -
b1 ?
b1 P
b0 ,
b0 @
b0 O
b10 +
b10 A
b10 N
b100010010000010010011 .
b100010010000010010011 >
b100010010000010010011 L
b100010010000010010011 W
b1001000 =
b1001000 X
b1000100 0
b1000100 ;
b1000100 V
b1000100 Y
15
#1800
05
#1850
b11 !
b11 K
b11 M
1"
1J
1(
1D
b1 -
b1 ?
b1 P
b11 +
b11 A
b11 N
b100010011000010010011 .
b100010011000010010011 >
b100010011000010010011 L
b100010011000010010011 W
b1001100 =
b1001100 X
b1001000 0
b1001000 ;
b1001000 V
b1001000 Y
15
#1900
05
#1950
b0 4
b0 7
b0 U
b0 !
b0 K
b0 M
0"
0J
0(
0D
b0 -
b0 ?
b0 P
b0 +
b0 A
b0 N
b110111 /
b110111 <
b110111 Q
b100010000000010110111 .
b100010000000010110111 >
b100010000000010110111 L
b100010000000010110111 W
b1010000 =
b1010000 X
b1001100 0
b1001100 ;
b1001100 V
b1001100 Y
15
#2000
05
#2050
b0 4
b0 7
b0 U
b100 +
b100 A
b100 N
b10111 /
b10111 <
b10111 Q
b100010100000010010111 .
b100010100000010010111 >
b100010100000010010111 L
b100010100000010010111 W
b1010100 =
b1010100 X
b1010000 0
b1010000 ;
b1010000 V
b1010000 Y
15
#2100
05
#2150
b10 -
b10 ?
b10 P
b1 !
b1 K
b1 M
1#
1I
b10 4
b10 7
b10 U
b10 3
b10 8
b10 T
b10 [
b1 2
b1 9
b1 S
b1 Z
b0 +
b0 A
b0 N
b10 1
b10 :
b10 R
b10 \
b1100011 /
b1100011 <
b1100011 Q
b1000001000000101100011 .
b1000001000000101100011 >
b1000001000000101100011 L
b1000001000000101100011 W
b1011000 =
b1011000 X
b1010100 0
b1010100 ;
b1010100 V
b1010100 Y
15
#2200
05
#2250
b1 !
b1 K
b1 M
1#
1I
b10 -
b10 ?
b10 P
b1 +
b1 A
b1 N
b1000001001000101100011 .
b1000001001000101100011 >
b1000001001000101100011 L
b1000001001000101100011 W
b1011100 =
b1011100 X
b1011000 0
b1011000 ;
b1011000 V
b1011000 Y
15
#2300
05
#2350
b1 !
b1 K
b1 M
1#
1I
b10 -
b10 ?
b10 P
b100 +
b100 A
b100 N
b1000001100000101100011 .
b1000001100000101100011 >
b1000001100000101100011 L
b1000001100000101100011 W
b1100000 =
b1100000 X
b1011100 0
b1011100 ;
b1011100 V
b1011100 Y
15
#2400
05
#2450
b1 !
b1 K
b1 M
1#
1I
b10 -
b10 ?
b10 P
b101 +
b101 A
b101 N
b1000001101000101100011 .
b1000001101000101100011 >
b1000001101000101100011 L
b1000001101000101100011 W
b1100100 =
b1100100 X
b1100000 0
b1100000 ;
b1100000 V
b1100000 Y
15
#2500
05
#2550
b1 !
b1 K
b1 M
1#
1I
b10 -
b10 ?
b10 P
b110 +
b110 A
b110 N
b1000001110000101100011 .
b1000001110000101100011 >
b1000001110000101100011 L
b1000001110000101100011 W
b1101000 =
b1101000 X
b1100100 0
b1100100 ;
b1100100 V
b1100100 Y
15
#2600
05
#2650
b1 !
b1 K
b1 M
1#
1I
b10 -
b10 ?
b10 P
b111 +
b111 A
b111 N
b1000001111000101100011 .
b1000001111000101100011 >
b1000001111000101100011 L
b1000001111000101100011 W
b1101100 =
b1101100 X
b1101000 0
b1101000 ;
b1101000 V
b1101000 Y
15
#2700
05
#2750
1$
1H
1"
1J
1(
1D
b0 !
b0 K
b0 M
0#
0I
b110000000000100 -
b110000000000100 ?
b110000000000100 P
b100 4
b100 7
b100 U
b100 3
b100 8
b100 T
b100 [
b0 2
b0 9
b0 S
b0 Z
b110 +
b110 A
b110 N
b1 1
b1 :
b1 R
b1 \
b1101111 /
b1101111 <
b1101111 Q
b10000000110000011101111 .
b10000000110000011101111 >
b10000000110000011101111 L
b10000000110000011101111 W
b1110000 =
b1110000 X
b1101100 0
b1101100 ;
b1101100 V
b1101100 Y
15
#2800
05
#2850
1$
1H
1"
1J
1(
1D
b100 -
b100 ?
b100 P
b1 2
b1 9
b1 S
b1 Z
b0 +
b0 A
b0 N
b10 1
b10 :
b10 R
b10 \
b1100111 /
b1100111 <
b1100111 Q
b10000001000000101100111 .
b10000001000000101100111 >
b10000001000000101100111 L
b10000001000000101100111 W
b1110100 =
b1110100 X
b1110000 0
b1110000 ;
b1110000 V
b1110000 Y
15
#2900
05
#2950
1%
1G
1&
1F
0$
0H
1"
1J
1(
1D
b0 -
b0 ?
b0 P
b0 4
b0 7
b0 U
b0 3
b0 8
b0 T
b0 [
b101 2
b101 9
b101 S
b101 Z
b10 +
b10 A
b10 N
b100 1
b100 :
b100 R
b100 \
b11 /
b11 <
b11 Q
b101010001000000011 .
b101010001000000011 >
b101010001000000011 L
b101010001000000011 W
b1111000 =
b1111000 X
b1110100 0
b1110100 ;
b1110100 V
b1110100 Y
15
#3000
05
#3050
1"
1J
1&
1F
1%
1G
1(
1D
b0 +
b0 A
b0 N
b101000001000000011 .
b101000001000000011 >
b101000001000000011 L
b101000001000000011 W
b1111100 =
b1111100 X
b1111000 0
b1111000 ;
b1111000 V
b1111000 Y
15
#3100
05
#3150
1"
1J
1&
1F
1%
1G
1(
1D
b1 +
b1 A
b1 N
b101001001000000011 .
b101001001000000011 >
b101001001000000011 L
b101001001000000011 W
b10000000 =
b10000000 X
b1111100 0
b1111100 ;
b1111100 V
b1111100 Y
15
#3200
05
#3250
1"
1J
1&
1F
1%
1G
1(
1D
b100 +
b100 A
b100 N
b101100001000000011 .
b101100001000000011 >
b101100001000000011 L
b101100001000000011 W
b10000100 =
b10000100 X
b10000000 0
b10000000 ;
b10000000 V
b10000000 Y
15
#3300
05
#3350
1"
1J
1&
1F
1%
1G
1(
1D
b101 +
b101 A
b101 N
b101101001000000011 .
b101101001000000011 >
b101101001000000011 L
b101101001000000011 W
b10001000 =
b10001000 X
b10000100 0
b10000100 ;
b10000100 V
b10000100 Y
15
#3400
05
#3450
1'
1E
1"
1J
0&
0F
0%
0G
0(
0D
b1 4
b1 7
b1 U
b1 3
b1 8
b1 T
b1 [
b10 2
b10 9
b10 S
b10 Z
b10 +
b10 A
b10 N
b0 1
b0 :
b0 R
b0 \
b100011 /
b100011 <
b100011 Q
b100010010000000100011 .
b100010010000000100011 >
b100010010000000100011 L
b100010010000000100011 W
b10001100 =
b10001100 X
b10001000 0
b10001000 ;
b10001000 V
b10001000 Y
15
#3500
05
#3550
1"
1J
1'
1E
b0 +
b0 A
b0 N
b100010000000000100011 .
b100010000000000100011 >
b100010000000000100011 L
b100010000000000100011 W
b10010000 =
b10010000 X
b10001100 0
b10001100 ;
b10001100 V
b10001100 Y
15
#3600
05
#3650
1"
1J
1'
1E
b1 +
b1 A
b1 N
b100010001000000100011 .
b100010001000000100011 >
b100010001000000100011 L
b100010001000000100011 W
b10010100 =
b10010100 X
b10010000 0
b10010000 ;
b10010000 V
b10010000 Y
15
#3700
05
#3750
b11 !
b11 K
b11 M
1(
1D
1"
1J
0'
0E
b0 4
b0 7
b0 U
b0 3
b0 8
b0 T
b0 [
b0 2
b0 9
b0 S
b0 Z
b0 +
b0 A
b0 N
b10011 /
b10011 <
b10011 Q
b10011 .
b10011 >
b10011 L
b10011 W
b10011000 =
b10011000 X
b10010100 0
b10010100 ;
b10010100 V
b10010100 Y
15
#3800
05
#3850
b10 !
b10 K
b10 M
0"
0J
1(
1D
b1 2
b1 9
b1 S
b1 Z
b10 1
b10 :
b10 R
b10 \
b110011 /
b110011 <
b110011 Q
b1000000100110011 .
b1000000100110011 >
b1000000100110011 L
b1000000100110011 W
b10011100 =
b10011100 X
b10011000 0
b10011000 ;
b10011000 V
b10011000 Y
15
#3900
05
#3950
1"
1J
b11 !
b11 K
b11 M
1(
1D
b0 2
b0 9
b0 S
b0 Z
b1 1
b1 :
b1 R
b1 \
b10011 /
b10011 <
b10011 Q
b10010011 .
b10010011 >
b10010011 L
b10010011 W
b10100000 =
b10100000 X
b10011100 0
b10011100 ;
b10011100 V
b10011100 Y
15
#4000
05
#4050
b110000000000100 -
b110000000000100 ?
b110000000000100 P
1$
1H
b0 !
b0 K
b0 M
1"
1J
1(
1D
b100 4
b100 7
b100 U
b100 3
b100 8
b100 T
b100 [
b110 +
b110 A
b110 N
b1101111 /
b1101111 <
b1101111 Q
b10000000110000011101111 .
b10000000110000011101111 >
b10000000110000011101111 L
b10000000110000011101111 W
b10100100 =
b10100100 X
b10100000 0
b10100000 ;
b10100000 V
b10100000 Y
15
